Workbook

Sheet 1BR Comps
A2: STR
C3: After OTA
A4: Cinematic Suite | Prime Location | Self Check-in - Apartments for Rent in Jeddah, Makkah Province, Saudi Arabia - Airbnb | B4: 654 | C4: =B4*(1-15%) -> 555.9
A5: Modern 1-Bed Apartment, Al Nahda, 75" TV - Apartments for Rent in Jeddah, Makkah Province, Saudi Arabia - Airbnb | B5: 400 | C5: =B5*(1-15%) -> 340
A6: Apartment in Al Nahdah. A4 - Apartments for Rent in Jeddah, Makkah Province, Saudi Arabia - Airbnb | B6: 407 | C6: =B6*(1-15%) -> 345.95
A7: KM Living | Green Crest Studio King Abdulaziz Road - Apartments for Rent in Jeddah, Makkah Province, Saudi Arabia - Airbnb | B7: 372 | C7: =B7*(1-15%) -> 316.2
A8: Luxury hotel-style one-bedroom apartment with a living room - King Road H1 - Apartments for Rent in Jeddah, Makkah Province, Saudi Arabia - Airbnb | B8: 489 | C8: =B8*(1-15%) -> 415.65
A9: Modern Cinema Suite | Giant Screen | Self Check-In - Apartments for Rent in Jeddah, Makkah Province, Saudi Arabia - Airbnb | B9: 779 | C9: =B9*(1-15%) -> 662.15
A10: Luxury hotel-style one-bedroom apartment with a living room - King Road H1 - Apartments for Rent in Jeddah, Makkah Province, Saudi Arabia - Airbnb | B10: 489 | C10: =B10*(1-15%) -> 415.65
A11: King Road - Luxury Suite - Apartments for Rent in Jeddah, Makkah Province, Saudi Arabia - Airbnb | B11: 431 | C11: =B11*(1-15%) -> 366.35
A12: Apartment in Al Nahdah. A1 - Apartments for Rent in Jeddah, Makkah Province, Saudi Arabia - Airbnb | B12: 432 | C12: =B12*(1-15%) -> 367.2
A13: Rozn Co|Stylish & Cozy 1BR 75" TV Self-Access - Apartments for Rent in Jeddah, Makkah Province, Saudi Arabia - Airbnb | B13: 450 | C13: =B13*(1-15%) -> 382.5
A14: Apartment 02 | Modern Cozy 85 Screen Near the Waterfront - Apartments for Rent in Jeddah, Makkah Province, Saudi Arabia - Airbnb | B14: 328 | C14: =B14*(1-15%) -> 278.8
A15: Modern 1-Bed Apartment, Al Nahda, 75" TV - Apartments for Rent in Jeddah, Makkah Province, Saudi Arabia - Airbnb | B15: 400 | C15: =B15*(1-15%) -> 340
A16: Cinematic Suite | Prime Location | Self Check-in - Apartments for Rent in Jeddah, Makkah Province, Saudi Arabia - Airbnb | B16: 645 | C16: =B16*(1-15%) -> 548.25
F20: Post - Cleaning fees | H20: Annual Projection
C21: =AVERAGE($C$4:$C$16) -> 410.35385 | D21: Average | F21: =C21-120 -> 290.35385 | H21: =F21*365*0.55 -> 58288.535
C22: =ROUND(AVERAGE($C$4:$C$16) -_xlfn.T.INV.2T(0.1, COUNT($C$4:$C$16)-1) * (_xlfn.STDEV.S($C$4:$C$16) / SQRT(COUNT($C$4:$C$16))),0) -> 355 | D22: Lowest | F22: =C22-120 -> 235 | H22: =F22*365*0.5 -> 42887.5
C23: =round(AVERAGE($C$4:$C$16) + _xlfn.T.INV.2T(0.05, COUNT($C$4:$C$16)-1) * (_xlfn.STDEV.S($C$4:$C$16) / SQRT(COUNT($C$4:$C$16))) ,0) -> 478 | D23: Highest | F23: =C23-120 -> 358 | H23: =F23*365*0.5 -> 65335

Sheet 2BR Comps
A2: STR | C2: After OTA
A3: Rozn Co|2BR Stylish & Cozy Apt Self Entry - Apartments for Rent in Jeddah, Makkah Province, Saudi Arabia - Airbnb | B3: 388 | C3: =B3*(1-15%) -> 329.8
A4: Two rooms and a spacious hall in Al-Nahda - Apartments for Rent in Jeddah, Makkah Province, Saudi Arabia - Airbnb | B4: 500 | C4: =B4*(1-15%) -> 425
A5: MONARCC (The epitome of luxury and sophistication) Suite 1 - Houses for Rent in Jeddah, Makkah Province, Saudi Arabia - Airbnb | B5: 614 | C5: =B5*(1-15%) -> 521.9
A6: Km living | Modern 2BR Apt King Abdulaziz Rd - Apartments for Rent in Jeddah, Makkah Province, Saudi Arabia - Airbnb | B6: 812 | C6: =B6*(1-15%) -> 690.2
A7: Luxury Stay | 2 Bedrooms and a Living Room | 75” TV | Al-Nahda | - Apartments for Rent in Jeddah, Makkah Province, Saudi Arabia - Airbnb | B7: 600 | C7: =B7*(1-15%) -> 510
A8: D2101 Two-Bedroom Apartment in Al-Nahda Neighborhood - Apartments for Rent in Jeddah, Makkah Province, Saudi Arabia - Airbnb | B8: 299 | C8: =B8*(1-15%) -> 254.15
A9: Luxury Apartment in Al-Nozha District - Near the Airport - Apartments for Rent in Jeddah, Makkah Province, Saudi Arabia - Airbnb | B9: 465 | C9: =B9*(1-15%) -> 395.25
A10: Comfortable 2BR Apartment | behind King Road - Apartments for Rent in Jeddah, Makkah Province, Saudi Arabia - Airbnb | B10: 525 | C10: =B10*(1-15%) -> 446.25
A11: Sara Residence | Elegant Modern 2BR | 75” TV - Apartments for Rent in Jeddah, Makkah Province, Saudi Arabia - Airbnb | B11: 640 | C11: =B11*(1-15%) -> 544
A12: Comfortable 2BR Apartment on King Abdulaziz Road - Apartments for Rent in Jeddah, Makkah Province, Saudi Arabia - Airbnb | B12: 550 | C12: =B12*(1-15%) -> 467.5
A13: Julia House | Julia House Jeddah - Apartments for Rent in Jeddah, Makkah Province, Saudi Arabia - Airbnb | B13: 268 | C13: =B13*(1-15%) -> 227.8
A14: Luxury apartment in Al-Nahda neighborhood with two bedrooms + an elegant living room. - Serviced apartments for Rent in Jeddah, Makkah Province, Saudi Arabia - Airbnb | B14: 480 | C14: =B14*(1-15%) -> 408
... A18: Elegant 2BR Stay –85”TV-Prime Location - Apartments for Rent in Jeddah, Makkah Province, Saudi Arabia - Airbnb | B18: 558 | C18: =B18*(1-15%) -> 474.3
A19: Luxury 2BR w/ 85 TV & Self Check-In” - Houses for Rent in Jeddah, Makkah Province, Saudi Arabia - Airbnb | B19: 773 | C19: =B19*(1-15%) -> 657.05 | J19: 55000
A20: Boutique 2BR Suite | Self Check-In |Prime Location - Apartments for Rent in Jeddah, Makkah Province, Saudi Arabia - Airbnb | B20: 796 | C20: =B20*(1-15%) -> 676.6 | J20: =J19/365*2 -> 301.36986
A21: Luxury 2 bedroom apartment 2R3B in Al-Nahda neighborhood - King Road - Apartments for Rent in Jeddah, Makkah Province, Saudi Arabia - Airbnb | B21: 793 | C21: =B21*(1-15%) -> 674.05 | J21: =J20*1.35 -> 406.84932
A22: Km living | 2BR King Abdulaziz-Luxury Stay - Apartments for Rent in Jeddah, Makkah Province, Saudi Arabia - Airbnb | B22: 824 | C22: =B22*(1-15%) -> 700.4
A23: King Road | Two Luxury Rooms | Self Check-in | Private Parking - Apartments for Rent in Jeddah, Makkah Province, Saudi Arabia - Airbnb | B23: 834 | C23: =B23*(1-15%) -> 708.9
A24: The Aura Loft - Lofts for Rent in Jeddah, Makkah Province, Saudi Arabia - Airbnb | B24: 940 | C24: =B24*(1-15%) -> 799
A25: KM Living | Green Crest 2BR + Maid | King Road - Apartments for Rent in Jeddah, Makkah Province, Saudi Arabia - Airbnb | B25: 790 | C25: =B25*(1-15%) -> 671.5
A32: =AVERAGE($C$3:$C$25) -> 520.60652 | B32: Average | D32: Cleaning | G32: Post - Cleaning fees
A33: =ROUND(AVERAGE($C$3:$C$25) -_xlfn.T.INV.2T(0.1, COUNT($C$3:$C$25)-1) * (_xlfn.STDEV.S($C$3:$C$25) / SQRT(COUNT($C$3:$C$25))),0) -> 463 | B33: Lowest | D33: 150 | G33: =A32-$D$33 -> 370.60652
A34: =round(AVERAGE($C$3:$C$25) + _xlfn.T.INV.2T(0.05, COUNT($C$3:$C$25)-1) * (_xlfn.STDEV.S($C$3:$C$25) / SQRT(COUNT($C$3:$C$25))) ,0) -> 591 | B34: Highest | G34: =A33-$D$33 -> 313
G35: =A34-$D$33 -> 441

Sheet LTR Financial Study
H6: Best Case | I6: Base Case | J6: Worst Case | K6: Type | L6: Unit
H7: ='1BR Comps'!$F$23*30 -> 10740 | I7: ='1BR Comps'!$F$21*30 -> 8710.6154 | J7: ='1BR Comps'!$F$22*30 -> 7050 | K7: 1Bd | L7: {=SEQUENCE(5,1,1,1)} -> 1
H8: ='1BR Comps'!$F$23*30 -> 10740 | I8: ='1BR Comps'!$F$21*30 -> 8710.6154 | J8: ='1BR Comps'!$F$22*30 -> 7050 | K8: 1Bd | L8: 2
H9: ='1BR Comps'!$F$23*30 -> 10740 | I9: ='1BR Comps'!$F$21*30 -> 8710.6154 | J9: ='1BR Comps'!$F$22*30 -> 7050 | K9: 1Bd | L9: 3
H10: ='2BR Comps'!$G$35*30 -> 13230 | I10: ='2BR Comps'!$G$33*30 -> 11118.196 | J10: ='2BR Comps'!$G$34*30 -> 9390 | K10: 2Bd | L10: 4
H11: ='2BR Comps'!$G$35*30 -> 13230 | I11: ='2BR Comps'!$G$33*30 -> 11118.196 | J11: ='2BR Comps'!$G$34*30 -> 9390 | K11: 2Bd | L11: 5
H13: =SUM(H$7:H$11)*12 -> 704160 | I13: =SUM(I$7:I$11)*12 -> 580418.85 | J13: =SUM(J$7:J$11)*12 -> 479160 | K13: Total

Sheet 2BR
A2: LTR Furnished | C2: LTR Unfurnished
A3: 65000 | B3: https://sa.aqar.fm/%D8%B4%D9%82%D9%82-%D9%84%D9%84%D8%A5%D9%8A%D8%AC%D8%A7%D8%B1/%D8%AC%D8%AF%D8%A9/%D8%B4%D9%85%D8%A7%D9%84-%D8%AC%D8%AF%D8%A9/%D8%AD%D9%8A-%D8%A7%D9%84%D9%86%D8%B2%D9%87%D8%A9/%D8%B4%D8%A7%D8%B1%D8%B9-%D8%B8%D9%8A%D8%A8%D8%A7%D9%86-%D8%A8%D9%86-%D8%B9%D9%85%D8%A7%D8%B1%D9%87-%D8%AD%D9%8A-%D8%A7%D9%84%D9%86%D8%B2%D9%87%D8%A9-%D8%AC%D8%AF%D8%A9-%D8%AC%D8%AF%D8%A9-6818284 | C3: 26000 | D3: https://sa.aqar.fm/%D8%B4%D9%82%D9%82-%D9%84%D9%84%D8%A5%D9%8A%D8%AC%D8%A7%D8%B1/%D8%AC%D8%AF%D8%A9/%D8%B4%D9%85%D8%A7%D9%84-%D8%AC%D8%AF%D8%A9/%D8%AD%D9%8A-%D8%A7%D9%84%D9%86%D8%B2%D9%87%D8%A9/%D8%B4%D8%A7%D8%B1%D8%B9-%D8%B7%D8%B1%D9%8A%D9%82-%D8%A7%D9%84%D9%85%D9%84%D9%83-%D9%81%D9%87%D8%AF-%D9%81%D8%B1%D8%B9%D9%8A-%D8%AD%D9%8A-%D8%A7%D9%84%D9%86%D8%B2%D9%87%D8%A9-%D9%85%D8%AF%D9%8A%D9%86%D8%A9-%D8%AC%D8%AF%D8%A9-%D9%85%D9%86%D8%B7%D9%82%D8%A9-%D9%85%D9%83%D8%A9-%D8%A7%D9%84%D9%85%D9%83%D8%B1%D9%85%D8%A9-6710325
A4: 27000 | B4: https://sa.aqar.fm/%D8%B4%D9%82%D9%82-%D9%84%D9%84%D8%A5%D9%8A%D8%AC%D8%A7%D8%B1/%D8%AC%D8%AF%D8%A9/%D8%B4%D9%85%D8%A7%D9%84-%D8%AC%D8%AF%D8%A9/%D8%AD%D9%8A-%D8%A7%D9%84%D9%86%D8%B2%D9%87%D8%A9/%D8%B4%D8%A7%D8%B1%D8%B9-%D8%B9%D8%AA%D9%8A%D8%A8%D9%87-%D8%A7%D9%84%D8%A8%D9%84%D9%88%D9%8A-%D8%AD%D9%8A-%D8%A7%D9%84%D9%86%D8%B2%D9%87%D8%A9-%D9%85%D8%AF%D9%8A%D9%86%D8%A9-%D8%AC%D8%AF%D8%A9-%D9%85%D9%86%D8%B7%D9%82%D8%A9-%D9%85%D9%83%D8%A9-%D8%A7%D9%84%D9%85%D9%83%D8%B1%D9%85%D8%A9-6668237 | C4: 33000 | D4: شقة للإيجار في شارع فرائد الضبطيه, حي النزهة, مدينة جدة, منطقة مكة المكرمة | تطبيق عقار
A5: 42000 | B5: https://sa.aqar.fm/%D8%B4%D9%82%D9%82-%D9%84%D9%84%D8%A5%D9%8A%D8%AC%D8%A7%D8%B1/%D8%AC%D8%AF%D8%A9/%D8%B4%D9%85%D8%A7%D9%84-%D8%AC%D8%AF%D8%A9/%D8%AD%D9%8A-%D8%A7%D9%84%D9%86%D8%B2%D9%87%D8%A9/%D8%B4%D8%A7%D8%B1%D8%B9-%D8%B7%D8%B1%D9%8A%D9%82-%D8%A7%D9%84%D9%85%D9%84%D9%83-%D9%81%D9%87%D8%AF-%D9%81%D8%B1%D8%B9%D9%8A-%D8%AD%D9%8A-%D8%A7%D9%84%D9%86%D8%B2%D9%87%D8%A9-%D9%85%D8%AF%D9%8A%D9%86%D8%A9-%D8%AC%D8%AF%D8%A9-%D9%85%D9%86%D8%B7%D9%82%D8%A9-%D9%85%D9%83%D8%A9-%D8%A7%D9%84%D9%85%D9%83%D8%B1%D9%85%D8%A9-6710325 | C5: 24000 | D5: شقة للإيجار في شارع البشام, حي النزهة, مدينة جدة, منطقة مكة المكرمة | تطبيق عقار
A6: 87000 | B6: https://sa.aqar.fm/%D8%B4%D9%82%D9%82-%D9%84%D9%84%D8%A5%D9%8A%D8%AC%D8%A7%D8%B1/%D8%AC%D8%AF%D8%A9/%D8%B4%D9%85%D8%A7%D9%84-%D8%AC%D8%AF%D8%A9/%D8%AD%D9%8A-%D8%A7%D9%84%D9%86%D8%B2%D9%87%D8%A9/%D8%B4%D8%A7%D8%B1%D8%B9-%D8%B8%D9%8A%D8%A8%D8%A7%D9%86-%D8%A8%D9%86-%D8%B9%D9%85%D8%A7%D8%B1%D9%87-%D8%AD%D9%8A-%D8%A7%D9%84%D9%86%D8%B2%D9%87%D8%A9-%D8%AC%D8%AF%D8%A9-%D8%AC%D8%AF%D8%A9-6616554 | C6: 34000 | D6: https://sa.aqar.fm/%D8%B4%D9%82%D9%82-%D9%84%D9%84%D8%A5%D9%8A%D8%AC%D8%A7%D8%B1/%D8%AC%D8%AF%D8%A9/%D8%B4%D9%85%D8%A7%D9%84-%D8%AC%D8%AF%D8%A9/%D8%AD%D9%8A-%D8%A7%D9%84%D9%86%D8%B2%D9%87%D8%A9/%D8%B4%D8%A7%D8%B1%D8%B9-%D9%86%D9%81%D9%88%D8%B2-%D9%82%D9%86%D9%81%D9%8A%D8%B0%D9%87-%D8%AD%D9%8A-%D8%A7%D9%84%D9%86%D8%B2%D9%87%D8%A9-%D9%85%D8%AF%D9%8A%D9%86%D8%A9-%D8%AC%D8%AF%D8%A9-%D9%85%D9%86%D8%B7%D9%82%D8%A9-%D9%85%D9%83%D8%A9-%D8%A7%D9%84%D9%85%D9%83%D8%B1%D9%85%D8%A9-6784169
A7: 26000 | B7: https://sa.aqar.fm/%D8%B4%D9%82%D9%82-%D9%84%D9%84%D8%A5%D9%8A%D8%AC%D8%A7%D8%B1/%D8%AC%D8%AF%D8%A9/%D8%B4%D9%85%D8%A7%D9%84-%D8%AC%D8%AF%D8%A9/%D8%AD%D9%8A-%D8%A7%D9%84%D9%86%D8%B2%D9%87%D8%A9/%D8%B4%D8%A7%D8%B1%D8%B9-%D8%B7%D8%B1%D9%8A%D9%82-%D8%A7%D9%84%D9%85%D9%84%D9%83-%D9%81%D9%87%D8%AF-%D9%81%D8%B1%D8%B9%D9%8A-%D8%AD%D9%8A-%D8%A7%D9%84%D9%86%D8%B2%D9%87%D8%A9-%D9%85%D8%AF%D9%8A%D9%86%D8%A9-%D8%AC%D8%AF%D8%A9-%D9%85%D9%86%D8%B7%D9%82%D8%A9-%D9%85%D9%83%D8%A9-%D8%A7%D9%84%D9%85%D9%83%D8%B1%D9%85%D8%A9-6714958 | C7: 33000 | D7: شقة للإيجار في شارع العام, حي النزهة, مدينة جدة, منطقة مكة المكرمة | تطبيق عقار
A8: 55000 | B8: شقة للإيجار في شارع سعيد البختري, حي النزهة, مدينة جدة, منطقة مكة المكرمة | تطبيق عقار | C8: 33000 | D8: شقة للإيجار في شارع العام, حي النزهة, مدينة جدة, منطقة مكة المكرمة | تطبيق عقار
A9: 23000 | B9: https://sa.aqar.fm/%D8%B4%D9%82%D9%82-%D9%84%D9%84%D8%A5%D9%8A%D8%AC%D8%A7%D8%B1/%D8%AC%D8%AF%D8%A9/%D8%B4%D9%85%D8%A7%D9%84-%D8%AC%D8%AF%D8%A9/%D8%AD%D9%8A-%D8%A7%D9%84%D9%86%D8%B2%D9%87%D8%A9/%D8%B4%D8%A7%D8%B1%D8%B9-%D9%85%D8%AD%D9%85%D8%AF-%D8%B3%D8%B9%D9%8A%D8%AF-%D9%86%D8%A7%D8%B5%D9%8A%D9%81-%D9%81%D8%B1%D8%B9%D9%8A-%D8%AD%D9%8A-%D8%A7%D9%84%D9%86%D8%B2%D9%87%D8%A9-%D9%85%D8%AF%D9%8A%D9%86%D8%A9-%D8%AC%D8%AF%D8%A9-%D9%85%D9%86%D8%B7%D9%82%D8%A9-%D9%85%D9%83%D8%A9-%D8%A7%D9%84%D9%85%D9%83%D8%B1%D9%85%D8%A9-6718582 | C9: 33000 | D9: شقة للإيجار في حي النزهة, مدينة جدة - 88061690 | بيوت السعودية
A10: 4000 | B10: https://sa.aqar.fm/%D8%B4%D9%82%D9%82-%D9%84%D9%84%D8%A5%D9%8A%D8%AC%D8%A7%D8%B1/%D8%AC%D8%AF%D8%A9/%D8%B4%D9%85%D8%A7%D9%84-%D8%AC%D8%AF%D8%A9/%D8%AD%D9%8A-%D8%A7%D9%84%D9%86%D8%B2%D9%87%D8%A9/%D8%B4%D8%A7%D8%B1%D8%B9-%D8%A7%D9%84%D8%AE%D9%85%D8%A7%D8%B3%D9%8A%D9%87-%D8%AD%D9%8A-%D8%A7%D9%84%D9%86%D8%B2%D9%87%D8%A9-%D9%85%D8%AF%D9%8A%D9%86%D8%A9-%D8%AC%D8%AF%D8%A9-%D9%85%D9%86%D8%B7%D9%82%D8%A9-%D9%85%D9%83%D8%A9-%D8%A7%D9%84%D9%85%D9%83%D8%B1%D9%85%D8%A9-6721049 | C10: 35000 | D10: شقة للإيجار في حي النزهة, مدينة جدة - 88061690 | بيوت السعودية
A11: 29000 | B11: شقة للإيجار في شارع القريبانيات, حي النزهة, مدينة جدة, منطقة مكة المكرمة | تطبيق عقار | C11: 38000 | D11: شقة للايجار في حي النزهة , جدة - 88040941 | بيوت السعودية
A12: 25000 | B12: شقة للإيجار في شارع الفضل اللهبي, حي النزهة, مدينة جدة, منطقة مكة المكرمة | تطبيق عقار | C12: 44000 | D12: شقة فاخرة للإيجار - 87836990 | بيوت السعودية | J12: Al Nuzha
A13: 36000 | B13: شقة للإيجار في شارع الخماسيه, حي النزهة, مدينة جدة, منطقة مكة المكرمة | تطبيق عقار
A14: =3800*12 -> 45600 | B14: شقة للإيجار في شارع الخماسيه, حي النزهة, مدينة جدة, منطقة مكة المكرمة | تطبيق عقار
A15: =3800*12 -> 45600 | B15: شقة للإيجار في شارع الخماسيه, حي النزهة, مدينة جدة, منطقة مكة المكرمة | تطبيق عقار
A16: =4000*12 -> 48000 | B16: شقة للإيجار في شارع الخماسيه, حي النزهة, مدينة جدة, منطقة مكة المكرمة | تطبيق عقار | D16: =AVERAGE(C3:C12) -> 33300 | E16: Average
A17: =3200*12 -> 38400 | B17: شقة للإيجار في شارع احمد الرقيمي, حي النزهة, مدينة جدة, منطقة مكة المكرمة | تطبيق عقار | D17: =ROUND(AVERAGE(C3:C12) -_xlfn.T.INV.2T(0.1, COUNT(C3:C12)-1) * (_xlfn.STDEV.S(C3:C12) / SQRT(COUNT($C$3:$C$12))),0) -> 30066 | E17: Lowest
A18: 55000 | B18: شقة للإيجار في شارع سعيد البختري, حي النزهة, مدينة جدة, منطقة مكة المكرمة | تطبيق عقار | D18: =round(AVERAGE(C$3:C$12) + _xlfn.T.INV.2T(0.05, COUNT(C$3:C$12)-1) * (_xlfn.STDEV.S(C$3:C$12) / SQRT(COUNT(C$3:C$12))) ,0) -> 37291 | E18: Highest
A19: 40000 | B19: شقة للايجار في حي النزهة , جدة - 88036038 | بيوت السعودية
A20: 42000 | B20: شقة للايجار في النزهة، شمال جدة - 88088856 | بيوت السعودية
A21: 44600 | B21: شقة مؤثثة للإيجار الشهري و السنوي في جدة حي النزهة - 87932446 | بيوت السعودية | D21: =D16/12 -> 2775 | E21: Average
A22: 45600 | B22: شقة مفروشة للإيجار الشهري في النزهة، شمال جدة - 87837533 | بيوت السعودية | D22: =D17/12 -> 2505.5 | E22: Lowest
D23: =D18/12 -> 3107.5833 | E23: Highest
A24: =AVERAGE(A3:A22) -> 41190 | B24: Average
A25: =ROUND(AVERAGE($A$3:$A$22) -_xlfn.T.INV.2T(0.1, COUNT($A$3:$A$22)-1) * (_xlfn.STDEV.S($A$3:$A$22) / SQRT(COUNT($A$3:$A$22))),0) -> 34459 | B25: Lowest | D25: Daily | G25: STR Multiplier | I25: 0.2 | K25: Target Occupancy | M25: 0.55 | O25: OTA Added | Q25: 0.15
A26: =round(AVERAGE($A$3:$A$22) + _xlfn.T.INV.2T(0.05, COUNT($A$3:$A$22)-1) * (_xlfn.STDEV.S($A$3:$A$22) / SQRT(COUNT($A$3:$A$22))) ,0) -> 49337 | B26: Highest | D26: =D21/30 -> 92.5 | E26: Average | G26: =D26*(1+$F$36) -> 111 | H26: Average | K26: =G26*(1+$J$36) -> 172.05 | L26: Average | O26: =K26*(1+$N$36) -> 197.8575 | P26: Average
D27: =D22/30 -> 83.516667 | E27: Lowest | G27: =D27*(1+$F$36) -> 100.22 | H27: Lowest | K27: =G27*(1+$J$36) -> 155.341 | L27: Lowest | O27: =K27*(1+$N$36) -> 178.64215 | P27: Lowest
D28: =D23/30 -> 103.58611 | E28: Highest | G28: =D28*(1+$F$36) -> 124.30333 | H28: Highest | K28: =G28*(1+$J$36) -> 192.67017 | L28: Highest | O28: =K28*(1+$N$36) -> 221.57069 | P28: Highest
A30: LTR Furnished
A32: =A24/12 -> 3432.5 | B32: Average
A33: =A25/12 -> 2871.5833 | B33: Lowest
A34: =A26/12 -> 4111.4167 | B34: Highest
A36: Daily | D36: STR Multiplier | F36: 0.2 | H36: Target Occupancy | J36: 0.55 | L36: OTA Added | N36: 0.15
A37: =A32/30 -> 114.41667 | B37: Average | D37: =A37*(1+$F$36) -> 137.3 | E37: Average | H37: =D37*(1+$J$36) -> 212.815 | I37: Average | L37: =H37*(1+$N$36) -> 244.73725 | M37: Average
A38: =A33/30 -> 95.719444 | B38: Lowest | D38: =A38*(1+$F$36) -> 114.86333 | E38: Lowest | H38: =D38*(1+$J$36) -> 178.03817 | I38: Lowest | L38: =H38*(1+$N$36) -> 204.74389 | M38: Lowest
A39: =A34/30 -> 137.04722 | B39: Highest | D39: =A39*(1+$F$36) -> 164.45667 | E39: Highest | H39: =D39*(1+$J$36) -> 254.90783 | I39: Highest | L39: =H39*(1+$N$36) -> 293.14401 | M39: Highest

Sheet LTR Study Summary
G9: Financial Study - Arqa
G10: Worst Case | L10: Base Case | P10: Best Case | T10: Scenarios
F11: ='LTR Financial Study'!J13 -> 479160 | L11: ='LTR Financial Study'!I13 -> 580418.85 | P11: ='LTR Financial Study'!H13 -> 704160 | T11: Revenue at 100% occupancy
F12: 0.6 | G12: 0.7 | H12: 0.8 | I12: 0.9 | K12: 0.6 | L12: 0.7 | M12: 0.8 | N12: 0.9 | O12: 0.6 | P12: 0.7 | Q12: 0.8 | R12: 0.9 | T12: Varying occupancy scenario
F13: =F12*F11 -> 287496 | G13: =F11*G12 -> 335412 | H13: =F11*H12 -> 383328 | I13: =F11*I12 -> 431244 | K13: =L11*K12 -> 348251.31 | L13: =L11*L12 -> 406293.19 | M13: =L11*M12 -> 464335.08 | N13: =L11*N12 -> 522376.96 | O13: =P11*O12 -> 422496 | P13: =P11*P12 -> 492912 | Q13: =P11*Q12 -> 563328 | R13: =P11*R12 -> 633744 | T13: Revenue pre deductions
F14: =F13*0.85 -> 244371.6 | G14: =G13*0.85 -> 285100.2 | H14: =H13*0.85 -> 325828.8 | I14: =I13*0.85 -> 366557.4 | K14: =K13*0.85 -> 296013.61 | L14: =L13*0.85 -> 345349.22 | M14: =M13*0.85 -> 394684.82 | N14: =N13*0.85 -> 444020.42 | O14: =O13*0.85 -> 359121.6 | P14: =P13*0.85 -> 418975.2 | Q14: =Q13*0.85 -> 478828.8 | R14: =R13*0.85 -> 538682.4 | T14: After Deducting VAT
F15: =F14*0.85 -> 207715.86 | G15: =G14*0.85 -> 242335.17 | H15: =H14*0.85 -> 276954.48 | I15: =I14*0.85 -> 311573.79 | K15: =K14*0.85 -> 251611.57 | L15: =L14*0.85 -> 293546.83 | M15: =M14*0.85 -> 335482.09 | N15: =N14*0.85 -> 377417.36 | O15: =O14*0.85 -> 305253.36 | P15: =P14*0.85 -> 356128.92 | Q15: =Q14*0.85 -> 407004.48 | R15: =R14*0.85 -> 457880.04 | T15: After Deducting OTA
F16: =F15*(1-$T$17) -> 159941.21 | G16: =G15*(1-$T$17) -> 186598.08 | H16: =H15*(1-$T$17) -> 213254.95 | I16: =I15*(1-$T$17) -> 239911.82 | K16: =K15*(1-$T$17) -> 193740.91 | L16: =L15*(1-$T$17) -> 226031.06 | M16: =M15*(1-$T$17) -> 258321.21 | N16: =N15*(1-$T$17) -> 290611.36 | O16: =O15*(1-$T$17) -> 235045.09 | P16: =P15*(1-$T$17) -> 274219.27 | Q16: =Q15*(1-$T$17) -> 313393.45 | R16: =R15*(1-$T$17) -> 352567.63 | T16: Net revenue after deducting Madinum share
T17: 0.23
F18: =F16/12/5 -> 2665.6869 | G18: =G16/12/5 -> 3109.968 | H18: =H16/12/5 -> 3554.2492 | I18: =I16/12/5 -> 3998.5303 | K18: =K16/12/5 -> 3229.0152 | L18: =L16/12/5 -> 3767.1844 | M18: =M16/12/5 -> 4305.3536 | N18: =N16/12/5 -> 4843.5227 | O18: =O16/12/5 -> 3917.4181 | P18: =P16/12/5 -> 4570.3211 | Q18: =Q16/12/5 -> 5223.2242 | R18: =R16/12/5 -> 5876.1272 | T18: Monthly Revenue per unit
F19: =F18*12 -> 31988.242 | G19: =G18*12 -> 37319.616 | H19: =H18*12 -> 42650.99 | I19: =I18*12 -> 47982.364 | K19: =K18*12 -> 38748.182 | L19: =L18*12 -> 45206.212 | M19: =M18*12 -> 51664.243 | N19: =N18*12 -> 58122.273 | O19: =O18*12 -> 47009.017 | P19: =P18*12 -> 54843.854 | Q19: =Q18*12 -> 62678.69 | R19: =R18*12 -> 70513.526 | T19: Annual Revenue per unit

Sheet STR Study Worksheet
O5: No. of units | P5: Type
O6: 4 | P6: 1Bd
O7: 2 | P7: Studio
O8: 3 | P8: 2Bd
L12: Financial Study - Al Nuzhah
F13: Worst Case | L13: Base Case | R13: Best Case | X13: Scenarios
F14: ='STR Financial Study'!J60 -> #REF! | L14: ='STR Financial Study'!I60 -> #REF! | R14: ='STR Financial Study'!H60 -> #REF! | X14: Revenue at 100% occupancy
F15: 0.4 | G15: 0.5 | H15: 0.6 | I15: 0.7 | J15: 0.8 | K15: 0.9 | L15: 0.4 | M15: 0.5 | N15: 0.6 | O15: 0.7 | P15: 0.8 | Q15: 0.9 | R15: 0.4 | S15: 0.5 | T15: 0.6 | U15: 0.7 | V15: 0.8 | W15: 0.9 | X15: Varying occupancy scenario
F16: =F14*F15 -> #REF! | G16: =F14*G15 -> #REF! | H16: =F14*H15 -> #REF! | I16: =F14*I15 -> #REF! | J16: =F14*J15 -> #REF! | K16: =F14*K15 -> #REF! | L16: =L14*L15 -> #REF! | M16: =L14*M15 -> #REF! | N16: =L14*N15 -> #REF! | O16: =L14*O15 -> #REF! | P16: =L14*P15 -> #REF! | Q16: =L14*Q15 -> #REF! | R16: =R14*R15 -> #REF! | S16: =R14*S15 -> #REF! | T16: =R14*T15 -> #REF! | U16: =R14*U15 -> #REF! | V16: =R14*V15 -> #REF! | W16: =R14*W15 -> #REF! | X16: Net revenue before deducting Mathwaa share
F17: Done | G17: Done | H17: Done | I17: Done | J17: Done | K17: Done | L17: Done | M17: Done | N17: Done | O17: Done | P17: Done | Q17: Done | R17: Done | S17: Done | T17: Done | U17: Done | V17: Done | W17: Done | X17: Dashboard Verification Status
F18: 265732 | G18: 332164 | H18: 398598 | I18: 465030 | J18: 531464 | K18: 597897 | L18: 323052 | M18: 403815 | N18: 484578 | O18: 565340 | P18: 646103 | Q18: 726866 | R18: 379906 | S18: 474883 | T18: 569860 | U18: 664836 | V18: 759813 | W18: 854790 | X18: Net revenue after deducting Mathwaa share 20%
F19: Done | G19: Done | H19: Done | I19: Done | J19: Done | K19: Done | L19: Done | M19: Done | N19: Done | O19: Done | P19: Done | Q19: Done | R19: Done | S19: Done | T19: Done | U19: Done | V19: Done | W19: Done | X19: Dashboard Verification Status
F20: 232515 | G20: 290644 | H20: 348773 | I20: 406901 | J20: 465031 | K20: 523159 | L20: 282679 | M20: 353338 | N20: 424005 | O20: 494673 | P20: 565341 | Q20: 636008 | R20: 332418 | S20: 415523 | T20: 498627 | U20: 581732 | V20: 664836 | W20: 747941 | X20: Net revenue after deducting Mathwaa share 30%
F21: Done | G21: Done | H21: Done | I21: Done | J21: Done | K21: Done | L21: Done | M21: Done | N21: Done | O21: Done | P21: Done | Q21: Done | R21: Done | S21: Done | T21: Done | U21: Done | V21: Done | W21: Done
