Workbook

Sheet FactSheet
B5: Location: | C5: https://maps.app.goo.gl/8a4RrkhsYPWJzmpX7?g_st=ic
B7: Features:
A8: 1 -
A9: 2 -
A10: 5 -
A11: 6-

Sheet STR-Studio-Master-Data
A1: Unit Type | B1: Average | C1: Minimum | D1: Maximum
A2: Studio | B2: =(D2+C2)/2 -> 445.65476 | C2: =B3 -> 263.30952 | D2: =MAX($H$11:$H$54) -> 628 | E2: Alternative Method
A3: Studio | B3: =AVERAGE($H$11:$H$54) -> 263.30952 | C3: =ROUND(AVERAGE($H$11:$H$54) -_xlfn.T.INV.2T(0.05, COUNT($H$11:$H$54)-1) * (_xlfn.STDEV.S($H$11:$H$54) / SQRT(COUNT($H$11:$H$54))),0) -> 239 | D3: =round(AVERAGE($H$11:$H$54) + _xlfn.T.INV.2T(0.05, COUNT($H$11:$H$54)-1) * (_xlfn.STDEV.S($H$11:$H$54) / SQRT(COUNT($H$11:$H$54))) ,0) -> 287 | E3: Ordinary Method
A9: Metrics
A10: ST.Deviation | B10: =STDEV($H$11:$H$54) -> 76.466313 | E10: Unit Name | F10: Type | G10: Status | H10: STR Price | I10: Link
A11: Median | B11: =MEDIAN($H$11:$H$54) -> 252.5 | E11: استديو واسع وانيق بمطبخ مستقل | F11: Studio | G11: Furnished | H11: 252 | I11: https://www.airbnb.com/rooms/1711418820103946781?check_in=2026-11-01&check_out=2026-11-02&search_mode=regular_search&source_impression_id=p3_9165ee25-8cfd-41ac-b297-2726e67bdf46_a6ea46ad-8e5b-4db0-b3e3-50d66509c602_0_1711418820103946781_11&previous_page_section_name=1000&federated_search_id=9165ee25-8cfd-41ac-b297-2726e67bdf46
A12: Average | B12: =round(AVERAGE($H$11:$H$54),0) -> 263 | E12: استديو هادئ وانيق بسرير ماستر | F12: Studio | G12: Furnished | H12: 294 | I12: https://www.airbnb.com/rooms/1504964401381763849?check_in=2026-11-01&check_out=2026-11-02&search_mode=regular_search&source_impression_id=p3_9165ee25-8cfd-41ac-b297-2726e67bdf46_a6ea46ad-8e5b-4db0-b3e3-50d66509c602_0_1504964401381763849_15&previous_page_section_name=1000&federated_search_id=9165ee25-8cfd-41ac-b297-2726e67bdf46
E13: شقة استديو بحوش خارجي وجلسة خارجيه ودخول ذاتي | F13: Studio | G13: Furnished | H13: 253 | I13: https://www.airbnb.com/rooms/1546240764834165219?check_in=2026-11-01&check_out=2026-11-02&search_mode=regular_search&source_impression_id=p3_d247e915-8630-4150-bcf0-55f2d8309172_c0270b2a-58d0-4782-8ec6-cacbfbfa0bc3_0_1546240764834165219_0&previous_page_section_name=1000&federated_search_id=d247e915-8630-4150-bcf0-55f2d8309172
E14: استديو دخول ذاتي (الياسمين) | F14: Studio | G14: Furnished | H14: 252 | I14: https://www.airbnb.com/rooms/1228163373545052064?check_in=2026-11-01&check_out=2026-11-02&search_mode=regular_search&source_impression_id=p3_d247e915-8630-4150-bcf0-55f2d8309172_c0270b2a-58d0-4782-8ec6-cacbfbfa0bc3_0_1228163373545052064_1&previous_page_section_name=1000&federated_search_id=d247e915-8630-4150-bcf0-55f2d8309172
E15: استديو ب حي الياسمين | F15: Studio | G15: Furnished | H15: 229 | I15: https://www.airbnb.com/rooms/1324806336396131989?check_in=2026-11-01&check_out=2026-11-02&search_mode=regular_search&source_impression_id=p3_d247e915-8630-4150-bcf0-55f2d8309172_c0270b2a-58d0-4782-8ec6-cacbfbfa0bc3_0_1324806336396131989_2&previous_page_section_name=1000&federated_search_id=d247e915-8630-4150-bcf0-55f2d8309172
E16: Studio with Back yard (Smart Entry) | F16: Studio | G16: Furnished | H16: 220 | I16: https://www.airbnb.com/rooms/1132902577296217698?check_in=2026-11-01&check_out=2026-11-02&search_mode=regular_search&source_impression_id=p3_d247e915-8630-4150-bcf0-55f2d8309172_c0270b2a-58d0-4782-8ec6-cacbfbfa0bc3_0_1132902577296217698_11&previous_page_section_name=1000&federated_search_id=d247e915-8630-4150-bcf0-55f2d8309172
E17: استيديو مريح مع فناء خارجي رائع | F17: Studio | G17: Furnished | H17: 380 | I17: https://www.airbnb.com/rooms/1201871230674753403?check_in=2026-11-01&check_out=2026-11-02&search_mode=regular_search&source_impression_id=p3_d247e915-8630-4150-bcf0-55f2d8309172_c0270b2a-58d0-4782-8ec6-cacbfbfa0bc3_0_1201871230674753403_13&previous_page_section_name=1000&federated_search_id=d247e915-8630-4150-bcf0-55f2d8309172
E18: استديو B6 لنقاهه والاستجمام الرياض- حي الياسمين | F18: Studio | G18: Furnished | H18: 282 | I18: https://www.airbnb.com/rooms/1618356522807534680?check_in=2026-11-01&check_out=2026-11-02&search_mode=regular_search&source_impression_id=p3_d247e915-8630-4150-bcf0-55f2d8309172_c0270b2a-58d0-4782-8ec6-cacbfbfa0bc3_0_1618356522807534680_12&previous_page_section_name=1000&federated_search_id=d247e915-8630-4150-bcf0-55f2d8309172
E19: 6C الياسمين شقه استديو أنيقه | F19: Studio | G19: Furnished | H19: 190 | I19: https://www.airbnb.com/rooms/1244110577238435004?check_in=2026-11-01&check_out=2026-11-02&search_mode=regular_search&source_impression_id=p3_d247e915-8630-4150-bcf0-55f2d8309172_c0270b2a-58d0-4782-8ec6-cacbfbfa0bc3_0_1244110577238435004_15&previous_page_section_name=1000&federated_search_id=d247e915-8630-4150-bcf0-55f2d8309172
E20: استديو هادئ وانيق بسرير ماستر | F20: Studio | G20: Furnished | H20: 294 | I20: https://www.airbnb.com/rooms/1613407666751592393?check_in=2026-11-01&check_out=2026-11-02&search_mode=regular_search&source_impression_id=p3_0005114e-d19b-4b2e-acc2-23ceaa248b92_5300222b-0009-4338-9258-5b990c4e7ccc_0_1613407666751592393_9&previous_page_section_name=1000&federated_search_id=0005114e-d19b-4b2e-acc2-23ceaa248b92
E21: Adidas Studio | F21: Studio | G21: Furnished | H21: 282 | I21: https://www.airbnb.com/rooms/1615121627928194543?check_in=2026-11-01&check_out=2026-11-02&search_mode=regular_search&source_impression_id=p3_0005114e-d19b-4b2e-acc2-23ceaa248b92_5300222b-0009-4338-9258-5b990c4e7ccc_0_1615121627928194543_12&previous_page_section_name=1000&federated_search_id=0005114e-d19b-4b2e-acc2-23ceaa248b92
E22: 4C comfy & cozy الياسمين | F22: Studio | G22: Furnished | H22: 190 | I22: https://www.airbnb.com/rooms/1291437635024792756?check_in=2026-11-01&check_out=2026-11-02&search_mode=regular_search&source_impression_id=p3_0005114e-d19b-4b2e-acc2-23ceaa248b92_5300222b-0009-4338-9258-5b990c4e7ccc_0_1291437635024792756_14&previous_page_section_name=1000&federated_search_id=0005114e-d19b-4b2e-acc2-23ceaa248b92
E23: استديو بتصميم مودرن | F23: Studio | G23: Furnished | H23: 254 | I23: https://www.airbnb.com/rooms/1484895520954567605?check_in=2026-11-01&check_out=2026-11-02&search_mode=regular_search&source_impression_id=p3_337973f2-5fae-4554-99f5-e34e49d8448b_b9db75bf-3dde-46f6-9d99-8db2c1e95854_0_1484895520954567605_0&previous_page_section_name=1000&federated_search_id=337973f2-5fae-4554-99f5-e34e49d8448b
E24: استديو مع جلسة خارجية بدخول ذاتي في الياسمين | F24: Studio | G24: Furnished | H24: 353 | I24: https://www.airbnb.com/rooms/1021192411440019469?check_in=2026-11-01&check_out=2026-11-02&search_mode=regular_search&source_impression_id=p3_337973f2-5fae-4554-99f5-e34e49d8448b_b9db75bf-3dde-46f6-9d99-8db2c1e95854_0_1021192411440019469_5&previous_page_section_name=1000&federated_search_id=337973f2-5fae-4554-99f5-e34e49d8448b
... E52: أستديو فاخر | F52: Studio | G52: Furnished | H52: 210 | I52: https://www.airbnb.com/rooms/1270705911149248148?check_in=2026-11-01&check_out=2026-11-02&search_mode=regular_search&source_impression_id=p3_995c1a87-5b3c-4baf-95da-cad58d2e60b1_ec52d7f6-3e0e-42ce-98f9-ca1efaafb1ac_0_1270705911149248148_8&previous_page_section_name=1000&federated_search_id=995c1a87-5b3c-4baf-95da-cad58d2e60b1
F53: Studio | G53: Furnished
F54: Studio | G54: Furnished

Sheet STR-1BR-Master-Data
A1: Unit Type | B1: Average | C1: Minimum | D1: Maximum
A2: 1Bd | B2: =(D2+C2)/2 -> 591.14773 | C2: =B3 -> 406.29545 | D2: =MAX($H$11:$H$54) -> 776 | E2: Alternative Method | I2: ملاحظة: يوجد تباين ملحوظ في العينة، كما أن ارتفاع المتوسط عن الوسيط يشير إلى تأثير بعض القيم المرتفعة على المتوسط.
A3: 1Bd | B3: =AVERAGE($H$11:$H$54) -> 406.29545 | C3: =ROUND(AVERAGE($H$11:$H$54) -_xlfn.T.INV.2T(0.05, COUNT($H$11:$H$54)-1) * (_xlfn.STDEV.S($H$11:$H$54) / SQRT(COUNT($H$11:$H$54))),0) -> 363 | D3: =round(AVERAGE($H$11:$H$54) + _xlfn.T.INV.2T(0.05, COUNT($H$11:$H$54)-1) * (_xlfn.STDEV.S($H$11:$H$54) / SQRT(COUNT($H$11:$H$54))) ,0) -> 449 | E3: Ordinary Method
A9: Metrics
A10: ST.Deviation | B10: =STDEV($H$11:$H$54) -> 141.94571 | E10: Unit Name | F10: Type | G10: Status | H10: STR Price | I10: Link
A11: Median | B11: =MEDIAN($H$11:$H$54) -> 365 | E11: شقة بصالة وغرفة نوم انيقة | F11: 1Bd | G11: Furnished | H11: 285 | I11: https://www.airbnb.com/rooms/1725241163796599020?check_in=2026-11-01&check_out=2026-11-02&search_mode=regular_search&source_impression_id=p3_875b0f56-8ba7-4871-858e-9fec5c011d04_e6a6dcb6-cacf-4f74-8667-9addda8daee6_0_1725241163796599020_1&previous_page_section_name=1000&federated_search_id=875b0f56-8ba7-4871-858e-9fec5c011d04
A12: Average | B12: =round(AVERAGE($H$11:$H$54),0) -> 406 | E12: Jasmine Apartment/ شقة الياسمين | F12: 1Bd | G12: Furnished | H12: 234 | I12: https://www.airbnb.com/rooms/1760293647028020262?check_in=2026-11-01&check_out=2026-11-02&search_mode=regular_search&source_impression_id=p3_875b0f56-8ba7-4871-858e-9fec5c011d04_e6a6dcb6-cacf-4f74-8667-9addda8daee6_0_1760293647028020262_2&previous_page_section_name=1000&federated_search_id=875b0f56-8ba7-4871-858e-9fec5c011d04
A13: Minimum | B13: =MIN(H11:H54) -> 220 | E13: شقة واسعه بمطبخ مستقل وغساله | F13: 1Bd | G13: Furnished | H13: 252 | I13: https://www.airbnb.com/rooms/1586391591595472231?check_in=2026-11-01&check_out=2026-11-02&search_mode=regular_search&source_impression_id=p3_875b0f56-8ba7-4871-858e-9fec5c011d04_e6a6dcb6-cacf-4f74-8667-9addda8daee6_0_1586391591595472231_6&previous_page_section_name=1000&federated_search_id=875b0f56-8ba7-4871-858e-9fec5c011d04
A14: Maximum | B14: =MAX(H11:H54) -> 776 | E14: Luxury Apartment | Spacious Living& Private Garden | F14: 1Bd | G14: Furnished | H14: 339 | I14: https://www.airbnb.com/rooms/1488457048378593402?check_in=2026-11-01&check_out=2026-11-02&search_mode=regular_search&source_impression_id=p3_875b0f56-8ba7-4871-858e-9fec5c011d04_e6a6dcb6-cacf-4f74-8667-9addda8daee6_0_1488457048378593402_9&previous_page_section_name=1000&federated_search_id=875b0f56-8ba7-4871-858e-9fec5c011d04
E15: Luxury 1BR | 75” QLED TV | Moon Bed | F15: 1Bd | G15: Furnished | H15: 485 | I15: https://www.airbnb.com/rooms/1488617192169510040?check_in=2026-11-01&check_out=2026-11-02&search_mode=regular_search&source_impression_id=p3_875b0f56-8ba7-4871-858e-9fec5c011d04_e6a6dcb6-cacf-4f74-8667-9addda8daee6_0_1488617192169510040_12&previous_page_section_name=1000&federated_search_id=875b0f56-8ba7-4871-858e-9fec5c011d04
E16: غرفة وصالة مودرن فاخرة B10 | F16: 1Bd | G16: Furnished | H16: 242 | I16: https://www.airbnb.com/rooms/1234709300695901118?check_in=2026-11-01&check_out=2026-11-02&search_mode=regular_search&source_impression_id=p3_875b0f56-8ba7-4871-858e-9fec5c011d04_e6a6dcb6-cacf-4f74-8667-9addda8daee6_0_1234709300695901118_13&previous_page_section_name=1000&federated_search_id=875b0f56-8ba7-4871-858e-9fec5c011d04
E17: شقة مكونة من غرفة نوم وصالة ومطبخ مستقل- دخول ذاتي | F17: 1Bd | G17: Furnished | H17: 286 | I17: https://www.airbnb.com/rooms/1718228819081743734?check_in=2026-11-01&check_out=2026-11-02&search_mode=regular_search&source_impression_id=p3_d247e915-8630-4150-bcf0-55f2d8309172_c0270b2a-58d0-4782-8ec6-cacbfbfa0bc3_0_1718228819081743734_4&previous_page_section_name=1000&federated_search_id=d247e915-8630-4150-bcf0-55f2d8309172
E18: Yas Home – 1BR Luxury Apartment - No Somking | F18: 1Bd | G18: Furnished | H18: 440 | I18: https://www.airbnb.com/rooms/1566943211087069608?check_in=2026-11-01&check_out=2026-11-02&search_mode=regular_search&source_impression_id=p3_d247e915-8630-4150-bcf0-55f2d8309172_c0270b2a-58d0-4782-8ec6-cacbfbfa0bc3_0_1566943211087069608_7&previous_page_section_name=1000&federated_search_id=d247e915-8630-4150-bcf0-55f2d8309172
E19: غرفه وصاله بتصميم مودرن | F19: 1Bd | G19: Furnished | H19: 394 | I19: https://www.airbnb.com/rooms/1197201288311766079?check_in=2026-11-01&check_out=2026-11-02&search_mode=regular_search&source_impression_id=p3_d247e915-8630-4150-bcf0-55f2d8309172_c0270b2a-58d0-4782-8ec6-cacbfbfa0bc3_0_1197201288311766079_8&previous_page_section_name=1000&federated_search_id=d247e915-8630-4150-bcf0-55f2d8309172
E20: شقة بتصميم مودرن ودخول ذكي | F20: 1Bd | G20: Furnished | H20: 323 | I20: https://www.airbnb.com/rooms/1488528599203217760?check_in=2026-11-01&check_out=2026-11-02&search_mode=regular_search&source_impression_id=p3_d247e915-8630-4150-bcf0-55f2d8309172_c0270b2a-58d0-4782-8ec6-cacbfbfa0bc3_0_1488528599203217760_10&previous_page_section_name=1000&federated_search_id=d247e915-8630-4150-bcf0-55f2d8309172
E21: شقة بصالة وغرفة نوم انيقة | F21: 1Bd | G21: Furnished | H21: 285 | I21: https://www.airbnb.com/rooms/1725241163796599020?check_in=2026-11-01&check_out=2026-11-02&search_mode=regular_search&source_impression_id=p3_875b0f56-8ba7-4871-858e-9fec5c011d04_e6a6dcb6-cacf-4f74-8667-9addda8daee6_0_1725241163796599020_1&previous_page_section_name=1000&federated_search_id=875b0f56-8ba7-4871-858e-9fec5c011d04
E22: شقة راقية وفاخرة بدخول ذاتي . | F22: 1Bd | G22: Furnished | H22: 559 | I22: https://www.airbnb.com/rooms/1199363001092225366?check_in=2026-11-01&check_out=2026-11-02&search_mode=regular_search&source_impression_id=p3_d247e915-8630-4150-bcf0-55f2d8309172_c0270b2a-58d0-4782-8ec6-cacbfbfa0bc3_0_1199363001092225366_14&previous_page_section_name=1000&federated_search_id=d247e915-8630-4150-bcf0-55f2d8309172
E23: Modern Spacious One-Bedroom Apartment in Al Yasmin | F23: 1Bd | G23: Furnished | H23: 365 | I23: https://www.airbnb.com/rooms/1576938055459886656?check_in=2026-11-01&check_out=2026-11-02&search_mode=regular_search&source_impression_id=p3_d247e915-8630-4150-bcf0-55f2d8309172_c0270b2a-58d0-4782-8ec6-cacbfbfa0bc3_0_1576938055459886656_17&previous_page_section_name=1000&federated_search_id=d247e915-8630-4150-bcf0-55f2d8309172
E24: Quiet and comfortable apartment | F24: 1Bd | G24: Furnished | H24: 330 | I24: https://www.airbnb.com/rooms/1461859458177390681?check_in=2026-11-01&check_out=2026-11-02&search_mode=regular_search&source_impression_id=p3_0005114e-d19b-4b2e-acc2-23ceaa248b92_5300222b-0009-4338-9258-5b990c4e7ccc_0_1461859458177390681_0&previous_page_section_name=1000&federated_search_id=0005114e-d19b-4b2e-acc2-23ceaa248b92
E25: الرياض-حي الياسمين-شارع الخيالة | F25: 1Bd | G25: Furnished | H25: 333 | I25: https://www.airbnb.com/rooms/1354288093759881828?check_in=2026-11-01&check_out=2026-11-02&search_mode=regular_search&source_impression_id=p3_0005114e-d19b-4b2e-acc2-23ceaa248b92_5300222b-0009-4338-9258-5b990c4e7ccc_0_1354288093759881828_1&previous_page_section_name=1000&federated_search_id=0005114e-d19b-4b2e-acc2-23ceaa248b92
E26: إقامة مريحة وقريبة من كل شيء | F26: 1Bd | G26: Furnished | H26: 314 | I26: https://www.airbnb.com/rooms/1631258049931636458?check_in=2026-11-01&check_out=2026-11-02&search_mode=regular_search&source_impression_id=p3_0005114e-d19b-4b2e-acc2-23ceaa248b92_5300222b-0009-4338-9258-5b990c4e7ccc_0_1631258049931636458_4&previous_page_section_name=1000&federated_search_id=0005114e-d19b-4b2e-acc2-23ceaa248b92
... E54: Apartment with One-Bedroom | F54: 1Bd | G54: Furnished | H54: 342 | I54: https://www.airbnb.com/rooms/1212054233269514580?check_in=2026-11-01&check_out=2026-11-02&search_mode=regular_search&source_impression_id=p3_995c1a87-5b3c-4baf-95da-cad58d2e60b1_ec52d7f6-3e0e-42ce-98f9-ca1efaafb1ac_0_1212054233269514580_9&previous_page_section_name=1000&federated_search_id=995c1a87-5b3c-4baf-95da-cad58d2e60b1

Sheet STR-2BR-Master-Data
A1: Unit Type | B1: Average | C1: Minimum | D1: Maximum
A2: 2Bd | B2: =(D2+C2)/2 -> 795.35294 | C2: =B3 -> 585.70588 | D2: =MAX($H$11:$H$27) -> 1005 | E2: Alternative Method
A3: 2Bd | B3: =AVERAGE($H$11:$H$27) -> 585.70588 | C3: =ROUND(AVERAGE($H$11:$H$27) -_xlfn.T.INV.2T(0.05, COUNT($H$11:$H$27)-1) * (_xlfn.STDEV.S($H$11:$H$27) / SQRT(COUNT($H$11:$H$27))),0) -> 483 | D3: =round(AVERAGE($H$11:$H$27) + _xlfn.T.INV.2T(0.05, COUNT($H$11:$H$27)-1) * (_xlfn.STDEV.S($H$11:$H$27) / SQRT(COUNT($H$11:$H$27))) ,0) -> 689 | E3: Ordinary Method
A9: Metrics
A10: ST.Deviation | B10: =STDEV($H$11:$H$27) -> 200.52143 | E10: Unit Name | F10: Type | G10: Status | H10: STR Price | I10: Link
A11: Median | B11: =MEDIAN($H$11:$H$27) -> 545 | E11: شقة فاخرة بغرفتين نوم 8 | F11: 2Bd | G11: Furnished | H11: 545 | I11: https://www.airbnb.com/rooms/1691344177896990977?check_in=2026-11-01&check_out=2026-11-02&search_mode=regular_search&source_impression_id=p3_256f262a-df40-46ff-a687-e4568bd3429e_cac85e21-98d8-461c-9934-d1dc4abbb7be_0_1691344177896990977_0&previous_page_section_name=1000&federated_search_id=256f262a-df40-46ff-a687-e4568bd3429e
A12: Average | B12: =round(AVERAGE($H$11:$H$27),0) -> 586 | E12: (12) غرفتين وصالة | F12: 2Bd | G12: Furnished | H12: 369 | I12: https://www.airbnb.com/rooms/1742848916354983452?check_in=2026-11-01&check_out=2026-11-02&search_mode=regular_search&source_impression_id=p3_256f262a-df40-46ff-a687-e4568bd3429e_cac85e21-98d8-461c-9934-d1dc4abbb7be_0_1742848916354983452_3&previous_page_section_name=1000&federated_search_id=256f262a-df40-46ff-a687-e4568bd3429e
A13: Minimum | B13: =MIN(H11:H27) -> 263 | E13: (B6) غرفتين وصالة | F13: 2Bd | G13: Furnished | H13: 393 | I13: https://www.airbnb.com/rooms/1745745139547335984?check_in=2026-11-01&check_out=2026-11-02&search_mode=regular_search&source_impression_id=p3_256f262a-df40-46ff-a687-e4568bd3429e_cac85e21-98d8-461c-9934-d1dc4abbb7be_0_1745745139547335984_11&previous_page_section_name=1000&federated_search_id=256f262a-df40-46ff-a687-e4568bd3429e
A14: Maximum | B14: =MAX(H11:H27) -> 1005 | E14: Spacious 2Bd APT | Cinema Room | F14: 2Bd | G14: Furnished | H14: 515 | I14: https://www.airbnb.com/rooms/1716647462756805887?check_in=2026-11-01&check_out=2026-11-02&search_mode=regular_search&source_impression_id=p3_256f262a-df40-46ff-a687-e4568bd3429e_cac85e21-98d8-461c-9934-d1dc4abbb7be_0_1716647462756805887_10&previous_page_section_name=1000&federated_search_id=256f262a-df40-46ff-a687-e4568bd3429e
E15: Spacious Luxury 2BR | 3 Beds | Cinema Room | F15: 2Bd | G15: Furnished | H15: 899 | I15: https://www.airbnb.com/rooms/1694459708079330352?check_in=2026-11-01&check_out=2026-11-02&search_mode=regular_search&source_impression_id=p3_256f262a-df40-46ff-a687-e4568bd3429e_cac85e21-98d8-461c-9934-d1dc4abbb7be_0_1694459708079330352_14&previous_page_section_name=1000&federated_search_id=256f262a-df40-46ff-a687-e4568bd3429e
E16: LUHA | Stylish 2BR• Spacious Living & Pool Table | F16: 2Bd | G16: Furnished | H16: 497 | I16: https://www.airbnb.com/rooms/1490143933220227464?check_in=2026-11-01&check_out=2026-11-02&search_mode=regular_search&source_impression_id=p3_256f262a-df40-46ff-a687-e4568bd3429e_cac85e21-98d8-461c-9934-d1dc4abbb7be_0_1490143933220227464_15&previous_page_section_name=1000&federated_search_id=256f262a-df40-46ff-a687-e4568bd3429e
E17: Elegant 2BR Self-check-in Apartment Near airport | F17: 2Bd | G17: Furnished | H17: 518 | I17: https://www.airbnb.com/rooms/1346525846695696852?check_in=2026-11-01&check_out=2026-11-02&search_mode=regular_search&source_impression_id=p3_256f262a-df40-46ff-a687-e4568bd3429e_cac85e21-98d8-461c-9934-d1dc4abbb7be_0_1346525846695696852_13&previous_page_section_name=1000&federated_search_id=256f262a-df40-46ff-a687-e4568bd3429e
E18: ٢٠٤شقة غرفتين وصالة جميلة في حي الياسمين | F18: 2Bd | G18: Furnished | H18: 365 | I18: https://www.airbnb.com/rooms/1144214324055135362?check_in=2026-11-01&check_out=2026-11-02&search_mode=regular_search&source_impression_id=p3_256f262a-df40-46ff-a687-e4568bd3429e_cac85e21-98d8-461c-9934-d1dc4abbb7be_0_1144214324055135362_18&previous_page_section_name=1000&federated_search_id=256f262a-df40-46ff-a687-e4568bd3429e
E19: شقة فاخرة بغرفتين نوم 5 | F19: 2Bd | G19: Furnished | H19: 595 | I19: https://www.airbnb.com/rooms/1706508631516515561?check_in=2026-11-01&check_out=2026-11-02&search_mode=regular_search&source_impression_id=p3_9c9f1301-2adb-46b3-accb-57672c7c274a_86512832-ab31-4c1c-9a51-49b9fdbcdef6_0_1706508631516515561_5&previous_page_section_name=1000&federated_search_id=9c9f1301-2adb-46b3-accb-57672c7c274a
E20: شقه فخمه وسط المدينة | F20: 2Bd | G20: Furnished | H20: 690 | I20: https://www.airbnb.com/rooms/1454873931369551794?check_in=2026-11-01&check_out=2026-11-02&search_mode=regular_search&source_impression_id=p3_9c9f1301-2adb-46b3-accb-57672c7c274a_86512832-ab31-4c1c-9a51-49b9fdbcdef6_0_1454873931369551794_8&previous_page_section_name=1000&federated_search_id=9c9f1301-2adb-46b3-accb-57672c7c274a
E21: Cozy 2BR Apt | Smart TV | Self Check-in | F21: 2Bd | G21: Furnished | H21: 263 | I21: https://www.airbnb.com/rooms/1660230672226847209?check_in=2026-11-01&check_out=2026-11-02&search_mode=regular_search&source_impression_id=p3_9c9f1301-2adb-46b3-accb-57672c7c274a_86512832-ab31-4c1c-9a51-49b9fdbcdef6_0_1660230672226847209_7&previous_page_section_name=1000&federated_search_id=9c9f1301-2adb-46b3-accb-57672c7c274a
E22: Luxury 2BR | Al Yasmin | Self Check-in | Near KAFD | F22: 2Bd | G22: Furnished | H22: 662 | I22: https://www.airbnb.com/rooms/1668240327800094077?check_in=2026-11-01&check_out=2026-11-02&search_mode=regular_search&source_impression_id=p3_9c9f1301-2adb-46b3-accb-57672c7c274a_86512832-ab31-4c1c-9a51-49b9fdbcdef6_0_1668240327800094077_6&previous_page_section_name=1000&federated_search_id=9c9f1301-2adb-46b3-accb-57672c7c274a
E23: Comfort stay - Mawrth | Unique - 2 BDR | F23: 2Bd | G23: Furnished | H23: 850 | I23: https://www.airbnb.com/rooms/1308716478216459483?check_in=2026-11-01&check_out=2026-11-02&search_mode=regular_search&source_impression_id=p3_b7b26e13-ffa5-4551-bbf6-19df67c26ce5_07ad6284-3bd7-4893-9242-dfc1e37f8f92_0_1308716478216459483_0&previous_page_section_name=1000&federated_search_id=b7b26e13-ffa5-4551-bbf6-19df67c26ce5
E24: Apartment in Al Yasmin - 008 | F24: 2Bd | G24: Furnished | H24: 693 | I24: https://www.airbnb.com/rooms/1116679511334084300?check_in=2026-11-01&check_out=2026-11-02&search_mode=regular_search&source_impression_id=p3_b7b26e13-ffa5-4551-bbf6-19df67c26ce5_07ad6284-3bd7-4893-9242-dfc1e37f8f92_0_1116679511334084300_2&previous_page_section_name=1000&federated_search_id=b7b26e13-ffa5-4551-bbf6-19df67c26ce5
E25: غرفتين وصالة بتصميم انيق وفاخر | F25: 2Bd | G25: Furnished | H25: 628 | I25: https://www.airbnb.com/rooms/1130705127199597345?check_in=2026-11-01&check_out=2026-11-02&search_mode=regular_search&source_impression_id=p3_b7b26e13-ffa5-4551-bbf6-19df67c26ce5_07ad6284-3bd7-4893-9242-dfc1e37f8f92_0_1130705127199597345_14&previous_page_section_name=1000&federated_search_id=b7b26e13-ffa5-4551-bbf6-19df67c26ce5
E26: Luxurious Minimalist Apartment - Al Yasmin - 007 | F26: 2Bd | G26: Furnished | H26: 1005 | I26: https://www.airbnb.com/rooms/1073813031897493474?check_in=2026-11-01&check_out=2026-11-02&search_mode=regular_search&source_impression_id=p3_f916e90d-830f-47ed-b443-ac9f75a0a985_096a6f67-813f-4b1c-bc29-ca9d3992cbba_0_1073813031897493474_8&previous_page_section_name=1000&federated_search_id=f916e90d-830f-47ed-b443-ac9f75a0a985
E27: مسكن صِبا ( J1 ) | F27: 2Bd | G27: Furnished | H27: 470 | I27: https://www.airbnb.com/rooms/1600054448229143550?check_in=2026-11-01&check_out=2026-11-02&search_mode=regular_search&source_impression_id=p3_f916e90d-830f-47ed-b443-ac9f75a0a985_096a6f67-813f-4b1c-bc29-ca9d3992cbba_0_1600054448229143550_11&previous_page_section_name=1000&federated_search_id=f916e90d-830f-47ed-b443-ac9f75a0a985

Sheet STR-3BR-Master-Data
A1: Unit Type | B1: Average | C1: Minimum | D1: Maximum
A2: 3BR | B2: =(D2+C2)/2 -> 862.15625 | C2: =B3 -> 774.3125 | D2: =MAX($H$11:$H$26) -> 950 | E2: Alternative Method
A3: 3BR | B3: =AVERAGE($H$11:$H$26) -> 774.3125 | C3: =ROUND(AVERAGE($H$11:$H$26) -_xlfn.T.INV.2T(0.05, COUNT($H$11:$H$26)-1) * (_xlfn.STDEV.S($H$11:$H$26) / SQRT(COUNT($H$11:$H$26))),0) -> 707 | D3: =round(AVERAGE($H$11:$H$26) + _xlfn.T.INV.2T(0.05, COUNT($H$11:$H$26)-1) * (_xlfn.STDEV.S($H$11:$H$26) / SQRT(COUNT($H$11:$H$26))) ,0) -> 842 | E3: Ordinary Method
A9: Metrics
A10: ST.Deviation | B10: =STDEV($H$11:$H$26) -> 126.67213 | E10: Unit Name | F10: Type | G10: Status | H10: STR Price | I10: Link
A11: Median | B11: =MEDIAN($H$11:$H$26) -> 776 | E11: Spacious Modern 3BR | Self check-in | F11: 3BR | G11: Furnished | H11: 899 | I11: https://www.airbnb.com/rooms/1725604666059844127?check_in=2026-11-01&check_out=2026-11-02&search_mode=regular_search&source_impression_id=p3_d46b2209-6cc2-4365-8cd2-7bda8882cfe8_a372b86b-fee2-4708-8e01-2da147019fae_0_1725604666059844127_1&previous_page_section_name=1000&federated_search_id=d46b2209-6cc2-4365-8cd2-7bda8882cfe8
A12: Average | B12: =round(AVERAGE($H$11:$H$26),0) -> 774 | E12: شقة مورث الياسمين 3 غرف | F12: 3BR | G12: Furnished | H12: 615 | I12: https://www.airbnb.com/rooms/1724543887172772859?check_in=2026-11-01&check_out=2026-11-02&search_mode=regular_search&source_impression_id=p3_d46b2209-6cc2-4365-8cd2-7bda8882cfe8_a372b86b-fee2-4708-8e01-2da147019fae_0_1724543887172772859_2&previous_page_section_name=1000&federated_search_id=d46b2209-6cc2-4365-8cd2-7bda8882cfe8
A13: Minimum | B13: =MIN(H11:H26) -> 430 | E13: شقة مورث B1 | F13: 3BR | G13: Furnished | H13: 776 | I13: https://www.airbnb.com/rooms/1282010387192707736?check_in=2026-11-01&check_out=2026-11-02&search_mode=regular_search&source_impression_id=p3_d46b2209-6cc2-4365-8cd2-7bda8882cfe8_a372b86b-fee2-4708-8e01-2da147019fae_0_1282010387192707736_5&previous_page_section_name=1000&federated_search_id=d46b2209-6cc2-4365-8cd2-7bda8882cfe8
A14: Maxim | B14: =MAX(H11:H26) -> 950 | E14: 3BR in Yasmeen+Self Checkin & Netflix Near Airport | F14: 3BR | G14: Furnished | H14: 430 | I14: https://www.airbnb.com/rooms/1767419610027838653?check_in=2026-11-01&check_out=2026-11-02&search_mode=regular_search&source_impression_id=p3_d46b2209-6cc2-4365-8cd2-7bda8882cfe8_a372b86b-fee2-4708-8e01-2da147019fae_0_1767419610027838653_6&previous_page_section_name=1000&federated_search_id=d46b2209-6cc2-4365-8cd2-7bda8882cfe8
E15: Stylish Modern Luxury 3BR Apartment | F15: 3BR | G15: Furnished | H15: 792 | I15: https://www.airbnb.com/rooms/1420405571643297849?check_in=2026-11-01&check_out=2026-11-02&search_mode=regular_search&source_impression_id=p3_d46b2209-6cc2-4365-8cd2-7bda8882cfe8_a372b86b-fee2-4708-8e01-2da147019fae_0_1420405571643297849_8&previous_page_section_name=1000&federated_search_id=d46b2209-6cc2-4365-8cd2-7bda8882cfe8
E16: شقة فاخرة 3 غرف نوم وغرفة ألعاب | F16: 3BR | G16: Furnished | H16: 720 | I16: https://www.airbnb.com/rooms/1674136255253184811?check_in=2026-11-01&check_out=2026-11-02&search_mode=regular_search&source_impression_id=p3_d46b2209-6cc2-4365-8cd2-7bda8882cfe8_a372b86b-fee2-4708-8e01-2da147019fae_0_1674136255253184811_7&previous_page_section_name=1000&federated_search_id=d46b2209-6cc2-4365-8cd2-7bda8882cfe8
E17: شقة مورث A9 | F17: 3BR | G17: Furnished | H17: 776 | I17: https://www.airbnb.com/rooms/1282082240731830982?check_in=2026-11-01&check_out=2026-11-02&search_mode=regular_search&source_impression_id=p3_d46b2209-6cc2-4365-8cd2-7bda8882cfe8_a372b86b-fee2-4708-8e01-2da147019fae_0_1282082240731830982_16&previous_page_section_name=1000&federated_search_id=d46b2209-6cc2-4365-8cd2-7bda8882cfe8
E18: Mabaat - Executive - Al Yasmin - 630 | F18: 3BR | G18: Furnished | H18: 859 | I18: https://www.airbnb.com/rooms/1648285070035468022?check_in=2026-11-01&check_out=2026-11-02&search_mode=regular_search&source_impression_id=p3_d46b2209-6cc2-4365-8cd2-7bda8882cfe8_a372b86b-fee2-4708-8e01-2da147019fae_0_1648285070035468022_18&previous_page_section_name=1000&federated_search_id=d46b2209-6cc2-4365-8cd2-7bda8882cfe8
E19: Luxury 3-Bedroom Residence in Al Yasmin | F19: 3BR | G19: Furnished | H19: 900 | I19: https://www.airbnb.com/rooms/1621883191914504575?check_in=2026-11-01&check_out=2026-11-02&search_mode=regular_search&source_impression_id=p3_d46b2209-6cc2-4365-8cd2-7bda8882cfe8_a372b86b-fee2-4708-8e01-2da147019fae_0_1621883191914504575_19&previous_page_section_name=1000&federated_search_id=d46b2209-6cc2-4365-8cd2-7bda8882cfe8
E20: Mabaat - Executive - Al Yasmin - 629 | F20: 3BR | G20: Furnished | H20: 859 | I20: https://www.airbnb.com/rooms/1653654652261939321?check_in=2026-11-01&check_out=2026-11-02&search_mode=regular_search&source_impression_id=p3_8d1a0895-b0c0-44d1-9731-fc61e8c1d089_bf03d9a4-f17d-4991-9925-3005ff41dbfd_0_1653654652261939321_5&previous_page_section_name=1000&federated_search_id=8d1a0895-b0c0-44d1-9731-fc61e8c1d089
E21: Living Space A19 | F21: 3BR | G21: Furnished | H21: 950 | I21: https://www.airbnb.com/rooms/1288557998780849889?check_in=2026-11-01&check_out=2026-11-02&search_mode=regular_search&source_impression_id=p3_8d1a0895-b0c0-44d1-9731-fc61e8c1d089_bf03d9a4-f17d-4991-9925-3005ff41dbfd_0_1288557998780849889_11&previous_page_section_name=1000&federated_search_id=8d1a0895-b0c0-44d1-9731-fc61e8c1d089
E22: 3BR+Maid Room Near Riyadh Front Expo+Solitaire Mal | F22: 3BR | G22: Furnished | H22: 758 | I22: https://www.airbnb.com/rooms/1349199807544507277?check_in=2026-11-01&check_out=2026-11-02&search_mode=regular_search&source_impression_id=p3_8d1a0895-b0c0-44d1-9731-fc61e8c1d089_bf03d9a4-f17d-4991-9925-3005ff41dbfd_0_1349199807544507277_14&previous_page_section_name=1000&federated_search_id=8d1a0895-b0c0-44d1-9731-fc61e8c1d089
E23: refal h | F23: 3BR | G23: Furnished | H23: 760 | I23: https://www.airbnb.com/rooms/1731378339534694548?check_in=2026-11-01&check_out=2026-11-02&search_mode=regular_search&source_impression_id=p3_8d1a0895-b0c0-44d1-9731-fc61e8c1d089_bf03d9a4-f17d-4991-9925-3005ff41dbfd_0_1731378339534694548_16&previous_page_section_name=1000&federated_search_id=8d1a0895-b0c0-44d1-9731-fc61e8c1d089
E24: شقة أساس الفاخرة | F24: 3BR | G24: Furnished | H24: 776 | I24: https://www.airbnb.com/rooms/1326540495344257969?check_in=2026-11-01&check_out=2026-11-02&search_mode=regular_search&source_impression_id=p3_8d1a0895-b0c0-44d1-9731-fc61e8c1d089_bf03d9a4-f17d-4991-9925-3005ff41dbfd_0_1326540495344257969_15&previous_page_section_name=1000&federated_search_id=8d1a0895-b0c0-44d1-9731-fc61e8c1d089
E25: شقة أنيقة | 3 غرف وصالة | مناسبة حتى 9 أشخاص وأكثر | F25: 3BR | G25: Furnished | H25: 670 | I25: https://www.airbnb.com/rooms/874750400724779641?check_in=2026-11-01&check_out=2026-11-02&search_mode=regular_search&source_impression_id=p3_1c20c537-801f-4f78-beb4-f990f2942397_aeecf51a-3cb5-41e7-9294-818cbcf94518_0_874750400724779641_1&previous_page_section_name=1000&federated_search_id=1c20c537-801f-4f78-beb4-f990f2942397
E26: Mabaat - Al Yasmin 3BR Apt - 605 | F26: 3BR | G26: Furnished | H26: 849 | I26: https://www.airbnb.com/rooms/1441979858152883377?check_in=2026-11-01&check_out=2026-11-02&search_mode=regular_search&source_impression_id=p3_1c20c537-801f-4f78-beb4-f990f2942397_aeecf51a-3cb5-41e7-9294-818cbcf94518_0_1441979858152883377_4&previous_page_section_name=1000&federated_search_id=1c20c537-801f-4f78-beb4-f990f2942397

Sheet STR-Regular Financial Study
C6: 1BR - 54 Units | H6: Best Case | I6: Base Case | J6: Worst Case | K6: Type | L6: Unit
H7: ='STR-1BR-Master-Data'!$D$3*30 -> 13470 | I7: ='STR-1BR-Master-Data'!$B$3*30 -> 12188.864 | J7: ='STR-1BR-Master-Data'!$C$3*30 -> 10890 | K7: 1Bd | L7: {=SEQUENCE(54,1,1,1)} -> 1
H8: ='STR-1BR-Master-Data'!$D$3*30 -> 13470 | I8: ='STR-1BR-Master-Data'!$B$3*30 -> 12188.864 | J8: ='STR-1BR-Master-Data'!$C$3*30 -> 10890 | K8: 1Bd | L8: 2
H9: ='STR-1BR-Master-Data'!$D$3*30 -> 13470 | I9: ='STR-1BR-Master-Data'!$B$3*30 -> 12188.864 | J9: ='STR-1BR-Master-Data'!$C$3*30 -> 10890 | K9: 1Bd | L9: 3
H10: ='STR-1BR-Master-Data'!$D$3*30 -> 13470 | I10: ='STR-1BR-Master-Data'!$B$3*30 -> 12188.864 | J10: ='STR-1BR-Master-Data'!$C$3*30 -> 10890 | K10: 1Bd | L10: 4
H11: ='STR-1BR-Master-Data'!$D$3*30 -> 13470 | I11: ='STR-1BR-Master-Data'!$B$3*30 -> 12188.864 | J11: ='STR-1BR-Master-Data'!$C$3*30 -> 10890 | K11: 1Bd | L11: 5
H12: ='STR-1BR-Master-Data'!$D$3*30 -> 13470 | I12: ='STR-1BR-Master-Data'!$B$3*30 -> 12188.864 | J12: ='STR-1BR-Master-Data'!$C$3*30 -> 10890 | K12: 1Bd | L12: 6
H13: ='STR-1BR-Master-Data'!$D$3*30 -> 13470 | I13: ='STR-1BR-Master-Data'!$B$3*30 -> 12188.864 | J13: ='STR-1BR-Master-Data'!$C$3*30 -> 10890 | K13: 1Bd | L13: 7
H14: ='STR-1BR-Master-Data'!$D$3*30 -> 13470 | I14: ='STR-1BR-Master-Data'!$B$3*30 -> 12188.864 | J14: ='STR-1BR-Master-Data'!$C$3*30 -> 10890 | K14: 1Bd | L14: 8
H15: ='STR-1BR-Master-Data'!$D$3*30 -> 13470 | I15: ='STR-1BR-Master-Data'!$B$3*30 -> 12188.864 | J15: ='STR-1BR-Master-Data'!$C$3*30 -> 10890 | K15: 1Bd | L15: 9
H16: ='STR-1BR-Master-Data'!$D$3*30 -> 13470 | I16: ='STR-1BR-Master-Data'!$B$3*30 -> 12188.864 | J16: ='STR-1BR-Master-Data'!$C$3*30 -> 10890 | K16: 1Bd | L16: 10
H17: ='STR-1BR-Master-Data'!$D$3*30 -> 13470 | I17: ='STR-1BR-Master-Data'!$B$3*30 -> 12188.864 | J17: ='STR-1BR-Master-Data'!$C$3*30 -> 10890 | K17: 1Bd | L17: 11
H18: ='STR-1BR-Master-Data'!$D$3*30 -> 13470 | I18: ='STR-1BR-Master-Data'!$B$3*30 -> 12188.864 | J18: ='STR-1BR-Master-Data'!$C$3*30 -> 10890 | K18: 1Bd | L18: 12
H19: ='STR-1BR-Master-Data'!$D$3*30 -> 13470 | I19: ='STR-1BR-Master-Data'!$B$3*30 -> 12188.864 | J19: ='STR-1BR-Master-Data'!$C$3*30 -> 10890 | K19: 1Bd | L19: 13
... H60: ='STR-1BR-Master-Data'!$D$3*30 -> 13470 | I60: ='STR-1BR-Master-Data'!$B$3*30 -> 12188.864 | J60: ='STR-1BR-Master-Data'!$C$3*30 -> 10890 | K60: 1Bd | L60: 54
H61: ='STR-2BR-Master-Data'!$D$3*30 -> 20670 | I61: ='STR-2BR-Master-Data'!$B$3*30 -> 17571.176 | J61: ='STR-2BR-Master-Data'!$C$3*30 -> 14490 | K61: 2Bd | L61: {=SEQUENCE(29,1,1,1)} -> 1
H62: ='STR-2BR-Master-Data'!$D$3*30 -> 20670 | I62: ='STR-2BR-Master-Data'!$B$3*30 -> 17571.176 | J62: ='STR-2BR-Master-Data'!$C$3*30 -> 14490 | K62: 2Bd | L62: 2
H63: ='STR-2BR-Master-Data'!$D$3*30 -> 20670 | I63: ='STR-2BR-Master-Data'!$B$3*30 -> 17571.176 | J63: ='STR-2BR-Master-Data'!$C$3*30 -> 14490 | K63: 2Bd | L63: 3
H64: ='STR-2BR-Master-Data'!$D$3*30 -> 20670 | I64: ='STR-2BR-Master-Data'!$B$3*30 -> 17571.176 | J64: ='STR-2BR-Master-Data'!$C$3*30 -> 14490 | K64: 2Bd | L64: 4
H65: ='STR-2BR-Master-Data'!$D$3*30 -> 20670 | I65: ='STR-2BR-Master-Data'!$B$3*30 -> 17571.176 | J65: ='STR-2BR-Master-Data'!$C$3*30 -> 14490 | K65: 2Bd | L65: 5
H66: ='STR-2BR-Master-Data'!$D$3*30 -> 20670 | I66: ='STR-2BR-Master-Data'!$B$3*30 -> 17571.176 | J66: ='STR-2BR-Master-Data'!$C$3*30 -> 14490 | K66: 2Bd | L66: 6
H67: ='STR-2BR-Master-Data'!$D$3*30 -> 20670 | I67: ='STR-2BR-Master-Data'!$B$3*30 -> 17571.176 | J67: ='STR-2BR-Master-Data'!$C$3*30 -> 14490 | K67: 2Bd | L67: 7
H68: ='STR-2BR-Master-Data'!$D$3*30 -> 20670 | I68: ='STR-2BR-Master-Data'!$B$3*30 -> 17571.176 | J68: ='STR-2BR-Master-Data'!$C$3*30 -> 14490 | K68: 2Bd | L68: 8
H69: ='STR-2BR-Master-Data'!$D$3*30 -> 20670 | I69: ='STR-2BR-Master-Data'!$B$3*30 -> 17571.176 | J69: ='STR-2BR-Master-Data'!$C$3*30 -> 14490 | K69: 2Bd | L69: 9
H70: ='STR-2BR-Master-Data'!$D$3*30 -> 20670 | I70: ='STR-2BR-Master-Data'!$B$3*30 -> 17571.176 | J70: ='STR-2BR-Master-Data'!$C$3*30 -> 14490 | K70: 2Bd | L70: 10
H71: ='STR-2BR-Master-Data'!$D$3*30 -> 20670 | I71: ='STR-2BR-Master-Data'!$B$3*30 -> 17571.176 | J71: ='STR-2BR-Master-Data'!$C$3*30 -> 14490 | K71: 2Bd | L71: 11
H72: ='STR-2BR-Master-Data'!$D$3*30 -> 20670 | I72: ='STR-2BR-Master-Data'!$B$3*30 -> 17571.176 | J72: ='STR-2BR-Master-Data'!$C$3*30 -> 14490 | K72: 2Bd | L72: 12
H73: ='STR-2BR-Master-Data'!$D$3*30 -> 20670 | I73: ='STR-2BR-Master-Data'!$B$3*30 -> 17571.176 | J73: ='STR-2BR-Master-Data'!$C$3*30 -> 14490 | K73: 2Bd | L73: 13
... H89: ='STR-2BR-Master-Data'!$D$3*30 -> 20670 | I89: ='STR-2BR-Master-Data'!$B$3*30 -> 17571.176 | J89: ='STR-2BR-Master-Data'!$C$3*30 -> 14490 | K89: 2Bd | L89: 29
H90: ='STR-3BR-Master-Data'!$D$3*30 -> 25260 | I90: ='STR-3BR-Master-Data'!$B$3*30 -> 23229.375 | J90: ='STR-3BR-Master-Data'!$C$3*30 -> 21210 | K90: 3BR | L90: 1
H91: ='STR-3BR-Master-Data'!$D$3*30 -> 25260 | I91: ='STR-3BR-Master-Data'!$B$3*30 -> 23229.375 | J91: ='STR-3BR-Master-Data'!$C$3*30 -> 21210 | K91: 3BR | L91: 2
H92: ='STR-3BR-Master-Data'!$D$3*30 -> 25260 | I92: ='STR-3BR-Master-Data'!$B$3*30 -> 23229.375 | J92: ='STR-3BR-Master-Data'!$C$3*30 -> 21210 | K92: 3BR | L92: 3
H94: =SUM(H$7:H$92)*12 -> 16831080 | I94: =SUM(I$7:I$92)*12 -> 14849411 | J94: =SUM(J$7:J$92)*12 -> 12862800 | K94: Total

Sheet STR-Regular Study Summary
L5: No. of units | M5: Type
L6: =COUNTA('STR-Regular Financial Study'!L7:L60) -> 54 | M6: 1Bd
L7: =COUNTA('STR-Regular Financial Study'!L61:L89) -> 29 | M7: 2Bd
L8: =3 -> 3 | M8: 3BR
F10: Financial Study - Leora
F11: Worst Case | L11: Base Case | Q11: Best Case | W11: Scenarios
F12: ='STR-Regular Financial Study'!J94 -> 12862800 | L12: ='STR-Regular Financial Study'!I94 -> 14849411 | Q12: ='STR-Regular Financial Study'!H94 -> 16831080 | W12: Revenue at 100% occupancy
F13: 0.5 | G13: 0.6 | H13: 0.7 | I13: 0.8 | J13: 0.9 | L13: 0.5 | M13: 0.6 | N13: 0.7 | O13: 0.8 | P13: 0.9 | Q13: 0.5 | R13: 0.6 | S13: 0.7 | T13: 0.8 | U13: 0.9 | W13: Varying occupancy scenario
F14: =$F$12*F13 -> 6431400 | G14: =$F$12*G13 -> 7717680 | H14: =$F$12*H13 -> 9003960 | I14: =$F$12*I13 -> 10290240 | J14: =$F$12*J13 -> 11576520 | L14: =$L$12*L13 -> 7424705.3 | M14: =$L$12*M13 -> 8909646.3 | N14: =$L$12*N13 -> 10394587 | O14: =$L$12*O13 -> 11879528 | P14: =$L$12*P13 -> 13364469 | Q14: =$Q$12*Q13 -> 8415540 | R14: =$Q$12*R13 -> 10098648 | S14: =$Q$12*S13 -> 11781756 | T14: =$Q$12*T13 -> 13464864 | U14: =$Q$12*U13 -> 15147972 | W14: Revenue pre deductions
F15: =F14*(1-$W$16) -> 5466690 | G15: =G14*(1-$W$16) -> 6560028 | H15: =H14*(1-$W$16) -> 7653366 | I15: =I14*(1-$W$16) -> 8746704 | J15: =J14*(1-$W$16) -> 9840042 | L15: =L14*(1-$W$16) -> 6310999.5 | M15: =M14*(1-$W$16) -> 7573199.4 | N15: =N14*(1-$W$16) -> 8835399.3 | O15: =O14*(1-$W$16) -> 10097599 | P15: =P14*(1-$W$16) -> 11359799 | Q15: =Q14*(1-$W$16) -> 7153209 | R15: =R14*(1-$W$16) -> 8583850.8 | S15: =S14*(1-$W$16) -> 10014493 | ... U15: =U14*(1-$W$16) -> 12875776 | W15: Post-OTA Revenues
W16: 0.15
F17: =F15*(1-$W$18) -> 4537352.7 | G17: =G15*(1-$W$18) -> 5444823.2 | H17: =H15*(1-$W$18) -> 6352293.8 | I17: =I15*(1-$W$18) -> 7259764.3 | J17: =J15*(1-$W$18) -> 8167234.9 | L17: =L15*(1-$W$18) -> 5238129.6 | M17: =M15*(1-$W$18) -> 6285755.5 | N17: =N15*(1-$W$18) -> 7333381.4 | O17: =O15*(1-$W$18) -> 8381007.3 | P17: =P15*(1-$W$18) -> 9428633.2 | Q17: =Q15*(1-$W$18) -> 5937163.5 | R17: =R15*(1-$W$18) -> 7124596.2 | S17: =S15*(1-$W$18) -> 8312028.9 | ... U17: =U15*(1-$W$18) -> 10686894 | W17: Net Revenue After deducting operaror fees
W18: 0.17
F21: =F17/SUM($L$6:$L$8) -> 52759.915 | G21: =G17/SUM($L$6:$L$8) -> 63311.898 | H21: =H17/SUM($L$6:$L$8) -> 73863.881 | I21: =I17/SUM($L$6:$L$8) -> 84415.864 | J21: =J17/SUM($L$6:$L$8) -> 94967.847 | L21: =L17/SUM($L$6:$L$8) -> 60908.483 | M21: =M17/SUM($L$6:$L$8) -> 73090.18 | N21: =N17/SUM($L$6:$L$8) -> 85271.877 | O21: =O17/SUM($L$6:$L$8) -> 97453.573 | P21: =P17/SUM($L$6:$L$8) -> 109635.27 | Q21: =Q17/SUM($L$6:$L$8) -> 69036.785 | R21: =R17/SUM($L$6:$L$8) -> 82844.141 | S21: =S17/SUM($L$6:$L$8) -> 96651.498 | ... U21: =U17/SUM($L$6:$L$8) -> 124266.21 | W21: Annual Revenue Per Unit
G22: =G14-#REF! -> #REF! | H22: =H14-#REF! -> #REF! | I22: =I14-#REF! -> #REF! | J22: =J14-#REF! -> #REF! | M22: =M14-#REF! -> #REF! | N22: =N14-#REF! -> #REF! | O22: =O14-#REF! -> #REF! | P22: =P14-#REF! -> #REF! | R22: =R14-#REF! -> #REF! | S22: =S14-#REF! -> #REF! | T22: =T14-#REF! -> #REF! | U22: =U14-#REF! -> #REF! | W22: Mathwa Gross Annual Commision
G23: =G22/18 -> #REF! | H23: =H22/18 -> #REF! | I23: =I22/18 -> #REF! | J23: =J22/18 -> #REF! | M23: =M22/18 -> #REF! | N23: =N22/18 -> #REF! | O23: =O22/18 -> #REF! | P23: =P22/18 -> #REF! | R23: =R22/18 -> #REF! | S23: =S22/18 -> #REF! | T23: =T22/18 -> #REF! | U23: =U22/18 -> #REF! | W23: Annual Commission per Unit
G24: =G23/' LTR Financial Study'!$I$7 -> #REF! | H24: =H23/' LTR Financial Study'!$I$7 -> #REF! | I24: =I23/' LTR Financial Study'!$I$7 -> #REF! | J24: =J23/' LTR Financial Study'!$I$7 -> #REF! | M24: =M23/#REF! -> #REF! | N24: =N23/#REF! -> #REF! | O24: =O23/#REF! -> #REF! | P24: =P23/#REF! -> #REF! | R24: =R23/' LTR Financial Study'!$J$7 -> #REF! | S24: =S23/' LTR Financial Study'!$J$7 -> #REF! | T24: =T23/' LTR Financial Study'!$J$7 -> #REF! | U24: =U23/' LTR Financial Study'!$J$7 -> #REF! | W24: Commission-To-Rent Ratio
F25: =F21/12 -> 4396.6596 | G25: =G21/12 -> 5275.9915 | H25: =H21/12 -> 6155.3234 | I25: =I21/12 -> 7034.6553 | J25: =J21/12 -> 7913.9873 | L25: =L21/12 -> 5075.7069 | M25: =M21/12 -> 6090.8483 | N25: =N21/12 -> 7105.9897 | O25: =O21/12 -> 8121.1311 | P25: =P21/12 -> 9136.2725 | Q25: =Q21/12 -> 5753.0654 | R25: =R21/12 -> 6903.6785 | S25: =S21/12 -> 8054.2915 | ... U25: =U21/12 -> 10355.518 | W25: Monthly Revenue Per Unit
F29: =F15-F17 -> 929337.3 | G29: =G15-G17 -> 1115204.8 | H29: =H15-H17 -> 1301072.2 | I29: =I15-I17 -> 1486939.7 | J29: =J15-J17 -> 1672807.1 | L29: =L15-L17 -> 1072869.9 | M29: =M15-M17 -> 1287443.9 | N29: =N15-N17 -> 1502017.9 | O29: =O15-O17 -> 1716591.9 | P29: =P15-P17 -> 1931165.8 | Q29: =Q15-Q17 -> 1216045.5 | R29: =R15-R17 -> 1459254.6 | S29: =S15-S17 -> 1702463.7 | ... U29: =U15-U17 -> 2188882 | W29: Operator Annual Revenue
F30: =F29/12 -> 77444.775 | G30: =G29/12 -> 92933.73 | H30: =H29/12 -> 108422.68 | I30: =I29/12 -> 123911.64 | J30: =J29/12 -> 139400.6 | L30: =L29/12 -> 89405.826 | M30: =M29/12 -> 107286.99 | N30: =N29/12 -> 125168.16 | O30: =O29/12 -> 143049.32 | P30: =P29/12 -> 160930.49 | Q30: =Q29/12 -> 101337.13 | R30: =R29/12 -> 121604.55 | S30: =S29/12 -> 141871.98 | ... U30: =U29/12 -> 182406.83 | W30: Operator Monthly Revenue

Sheet Ltr-1BR-Master-Data
A1: Unit Type | B1: Average | C1: Minimum | D1: Maximum
A2: 1Bd | B2: =(D2+C2)/2 -> 5194.5 | C2: =B3 -> 4500 | D2: =MAX($H$11:$H$25) -> 5889 | E2: Alternative Method
A3: 1Bd | B3: 4500 | C3: 4200 | D3: 4900 | E3: Ordinary Method
A9: Metrics
A10: ST.Deviation | B10: =STDEV($H$11:$H$25) -> 1036.4754 | E10: Unit Name | F10: Type | G10: Status | H10: LTR Price | I10: Link
A11: Median | B11: =MEDIAN($H$11:$H$25) -> 4000 | E11: 1 Bedroom Studio For Rent in Al Yasmin, Riyadh شقق أكنان العز | F11: 1Bd | G11: Furnished | H11: 3000 | I11: https://www.bayut.sa/%D8%A7%D9%84%D8%B9%D9%82%D8%A7%D8%B1/%D8%AA%D9%81%D8%A7%D8%B5%D9%8A%D9%84-87977183.html
A12: Average | B12: =round(AVERAGE($H$11:$H$25),0) -> 4059 | E12: غرفة وصالة في حي الياسمين | F12: 1Bd | G12: Furnished | H12: =60000/12 -> 5000 | I12: https://www.bayut.sa/%D8%A7%D9%84%D8%B9%D9%82%D8%A7%D8%B1/%D8%AA%D9%81%D8%A7%D8%B5%D9%8A%D9%84-87968877.html
A13: Minimum | B13: =MIN(H11:H25) -> 2833.3333 | E13: شقة للإيجار في الياسمين، شمال الرياض | F13: 1Bd | G13: Furnished | H13: 4000 | I13: https://www.bayut.sa/%D8%A7%D9%84%D8%B9%D9%82%D8%A7%D8%B1/%D8%AA%D9%81%D8%A7%D8%B5%D9%8A%D9%84-87800815.html
A14: Maximum | B14: =MAX(H11:H25) -> 5889 | E14: ستوديو #1 | F14: 1Bd | G14: Furnished | H14: =45000/12 -> 3750 | I14: https://www.bayut.sa/%D8%A7%D9%84%D8%B9%D9%82%D8%A7%D8%B1/%D8%AA%D9%81%D8%A7%D8%B5%D9%8A%D9%84-87908124.html
E15: شقة للايجار في حي الياسمين، شمال الرياض | F15: 1Bd | G15: Furnished | H15: =34000/12 -> 2833.3333 | I15: https://www.bayut.sa/%D8%A7%D9%84%D8%B9%D9%82%D8%A7%D8%B1/%D8%AA%D9%81%D8%A7%D8%B5%D9%8A%D9%84-88038303.html
E16: 1 Bedroom Apartment For Rent in Al Yasmin, Riyadh شقق أكنان العز | F16: 1Bd | G16: Furnished | H16: 3500 | I16: https://www.bayut.sa/%D8%A7%D9%84%D8%B9%D9%82%D8%A7%D8%B1/%D8%AA%D9%81%D8%A7%D8%B5%D9%8A%D9%84-87964958.html
E17: شقة مفروشة من غرفة نوم واحدة للإيجار في الياسمين، الرياض | F17: 1Bd | G17: Furnished | H17: 5889 | I17: https://www.bayut.sa/%D8%A7%D9%84%D8%B9%D9%82%D8%A7%D8%B1/%D8%AA%D9%81%D8%A7%D8%B5%D9%8A%D9%84-87997915.html
E18: شقة للإيجار في الياسمين، شمال الرياض | F18: 1Bd | G18: Furnished | H18: 5000 | I18: https://www.bayut.sa/%D8%A7%D9%84%D8%B9%D9%82%D8%A7%D8%B1/%D8%AA%D9%81%D8%A7%D8%B5%D9%8A%D9%84-88018571.html
E19: شقق أكنان العز شقة للإيجار السنوي – الرياض | حي الياسمين | F19: 1Bd | G19: Furnished | H19: =38500/12 -> 3208.3333 | I19: https://www.bayut.sa/%D8%A7%D9%84%D8%B9%D9%82%D8%A7%D8%B1/%D8%AA%D9%81%D8%A7%D8%B5%D9%8A%D9%84-88039175.html
E20: شقق أكنان العز شقة الياسمين – للإيجار السنوي | F20: 1Bd | G20: Furnished | H20: =48500/12 -> 4041.6667 | I20: https://www.bayut.sa/%D8%A7%D9%84%D8%B9%D9%82%D8%A7%D8%B1/%D8%AA%D9%81%D8%A7%D8%B5%D9%8A%D9%84-88039172.html
E21: شقة للايجار في حي الياسمين، شمال الرياض | F21: 1Bd | G21: Furnished | H21: =34000/12 -> 2833.3333 | I21: https://www.bayut.sa/%D8%A7%D9%84%D8%B9%D9%82%D8%A7%D8%B1/%D8%AA%D9%81%D8%A7%D8%B5%D9%8A%D9%84-88038301.html
E22: شقة للايجار في حي الياسمين، شمال الرياض | F22: 1Bd | G22: Furnished | H22: =34000/12 -> 2833.3333 | I22: https://www.bayut.sa/%D8%A7%D9%84%D8%B9%D9%82%D8%A7%D8%B1/%D8%AA%D9%81%D8%A7%D8%B5%D9%8A%D9%84-88038302.html
E23: شقة مفروشة بغرفة نوم واحدة للإيجار في الياسمن، الرياض | F23: 1Bd | G23: Furnished | H23: =66000/12 -> 5500 | I23: https://www.bayut.sa/%D8%A7%D9%84%D8%B9%D9%82%D8%A7%D8%B1/%D8%AA%D9%81%D8%A7%D8%B5%D9%8A%D9%84-87974195.html
E24: غرفة وصالة في حي الياسمين | F24: 1Bd | G24: Furnished | H24: =60000/12 -> 5000 | I24: https://www.bayut.sa/%D8%A7%D9%84%D8%B9%D9%82%D8%A7%D8%B1/%D8%AA%D9%81%D8%A7%D8%B5%D9%8A%D9%84-87968877.html
E25: شقة للايجار في الياسمين، شمال الرياض | F25: 1Bd | G25: Furnished | H25: =54000/12 -> 4500 | I25: https://www.bayut.sa/%D8%A7%D9%84%D8%B9%D9%82%D8%A7%D8%B1/%D8%AA%D9%81%D8%A7%D8%B5%D9%8A%D9%84-88032679.html

Sheet LTR-2BR-Master-Data
A1: Unit Type | B1: Average | C1: Minimum | D1: Maximum
A2: 2Bd | B2: =(D2+C2)/2 -> 10631.458 | C2: =B3 -> 7762.9167 | D2: =MAX($H$11:$H$26) -> 13500 | E2: Alternative Method
A3: 2Bd | B3: =AVERAGE($H$11:$H$26) -> 7762.9167 | C3: =ROUND(AVERAGE($H$11:$H$26) -_xlfn.T.INV.2T(0.05, COUNT($H$11:$H$26)-1) * (_xlfn.STDEV.S($H$11:$H$26) / SQRT(COUNT($H$11:$H$26))),0) -> 6730 | D3: =round(AVERAGE($H$11:$H$26) + _xlfn.T.INV.2T(0.05, COUNT($H$11:$H$26)-1) * (_xlfn.STDEV.S($H$11:$H$26) / SQRT(COUNT($H$11:$H$26))) ,0) -> 8796 | E3: Ordinary Method
A9: Metrics
A10: ST.Deviation | B10: =STDEV($H$11:$H$26) -> 1937.8671 | E10: Unit Name | F10: Type | G10: Status | H10: STR Price | I10: Link
A11: Median | B11: =MEDIAN($H$11:$H$26) -> 7083.3333 | E11: شقة للإيجار في شارع الخيالة, حي الياسمين, مدينة الرياض, منطقة الرياض | F11: 2Bd | G11: Furnished | H11: =85000/12 -> 7083.3333 | I11: https://sa.aqar.fm/%D8%B4%D9%82%D9%82-%D9%84%D9%84%D8%A5%D9%8A%D8%AC%D8%A7%D8%B1/%D8%A7%D9%84%D8%B1%D9%8A%D8%A7%D8%B6/%D8%B4%D9%85%D8%A7%D9%84-%D8%A7%D9%84%D8%B1%D9%8A%D8%A7%D8%B6/%D8%AD%D9%8A-%D8%A7%D9%84%D9%8A%D8%A7%D8%B3%D9%85%D9%8A%D9%86/%D8%B4%D8%A7%D8%B1%D8%B9-%D8%A7%D9%84%D8%AE%D9%8A%D8%A7%D9%84%D8%A9-%D8%AD%D9%8A-%D8%A7%D9%84%D9%8A%D8%A7%D8%B3%D9%85%D9%8A%D9%86-%D9%85%D8%AF%D9%8A%D9%86%D8%A9-%D8%A7%D9%84%D8%B1%D9%8A%D8%A7%D8%B6-%D9%85%D9%86%D8%B7%D9%82%D8%A9-%D8%A7%D9%84%D8%B1%D9%8A%D8%A7%D8%B6-6804404
A12: Average | B12: =round(AVERAGE($H$11:$H$26),0) -> 7763 | E12: شقة للإيجار في شارع الفجر, حي الياسمين, مدينة الرياض, منطقة الرياض | F12: 2Bd | G12: Furnished | H12: =80000/12 -> 6666.6667 | I12: https://sa.aqar.fm/%D8%B4%D9%82%D9%82-%D9%84%D9%84%D8%A5%D9%8A%D8%AC%D8%A7%D8%B1/%D8%A7%D9%84%D8%B1%D9%8A%D8%A7%D8%B6/%D8%B4%D9%85%D8%A7%D9%84-%D8%A7%D9%84%D8%B1%D9%8A%D8%A7%D8%B6/%D8%AD%D9%8A-%D8%A7%D9%84%D9%8A%D8%A7%D8%B3%D9%85%D9%8A%D9%86/%D8%B4%D8%A7%D8%B1%D8%B9-%D8%A7%D9%84%D9%81%D8%AC%D8%B1-%D8%AD%D9%8A-%D8%A7%D9%84%D9%8A%D8%A7%D8%B3%D9%85%D9%8A%D9%86-%D9%85%D8%AF%D9%8A%D9%86%D8%A9-%D8%A7%D9%84%D8%B1%D9%8A%D8%A7%D8%B6-%D9%85%D9%86%D8%B7%D9%82%D8%A9-%D8%A7%D9%84%D8%B1%D9%8A%D8%A7%D8%B6-6816735
A13: Minimum | B13: =MIN(H11:H26) -> 5416.6667 | E13: شقة للإيجار في شارع القادسية, حي الياسمين, مدينة الرياض, منطقة الرياض | F13: 2Bd | G13: Furnished | H13: 10500 | I13: https://sa.aqar.fm/%D8%B4%D9%82%D9%82-%D9%84%D9%84%D8%A5%D9%8A%D8%AC%D8%A7%D8%B1/%D8%A7%D9%84%D8%B1%D9%8A%D8%A7%D8%B6/%D8%B4%D9%85%D8%A7%D9%84-%D8%A7%D9%84%D8%B1%D9%8A%D8%A7%D8%B6/%D8%AD%D9%8A-%D8%A7%D9%84%D9%8A%D8%A7%D8%B3%D9%85%D9%8A%D9%86/%D8%B4%D8%A7%D8%B1%D8%B9-%D8%A7%D9%84%D9%82%D8%A7%D8%AF%D8%B3%D9%8A%D8%A9-%D8%AD%D9%8A-%D8%A7%D9%84%D9%8A%D8%A7%D8%B3%D9%85%D9%8A%D9%86-%D9%85%D8%AF%D9%8A%D9%86%D8%A9-%D8%A7%D9%84%D8%B1%D9%8A%D8%A7%D8%B6-%D9%85%D9%86%D8%B7%D9%82%D8%A9-%D8%A7%D9%84%D8%B1%D9%8A%D8%A7%D8%B6-6529452
A14: Maximum | B14: =MAX(H11:H26) -> 13500 | E14: شقة للإيجار في شارع القادسية, حي الياسمين, مدينة الرياض, منطقة الرياض | F14: 2Bd | G14: Furnished | H14: 13500 | I14: https://sa.aqar.fm/%D8%B4%D9%82%D9%82-%D9%84%D9%84%D8%A5%D9%8A%D8%AC%D8%A7%D8%B1/%D8%A7%D9%84%D8%B1%D9%8A%D8%A7%D8%B6/%D8%B4%D9%85%D8%A7%D9%84-%D8%A7%D9%84%D8%B1%D9%8A%D8%A7%D8%B6/%D8%AD%D9%8A-%D8%A7%D9%84%D9%8A%D8%A7%D8%B3%D9%85%D9%8A%D9%86/%D8%B4%D8%A7%D8%B1%D8%B9-%D8%A7%D9%84%D9%82%D8%A7%D8%AF%D8%B3%D9%8A%D8%A9-%D8%AD%D9%8A-%D8%A7%D9%84%D9%8A%D8%A7%D8%B3%D9%85%D9%8A%D9%86-%D9%85%D8%AF%D9%8A%D9%86%D8%A9-%D8%A7%D9%84%D8%B1%D9%8A%D8%A7%D8%B6-%D9%85%D9%86%D8%B7%D9%82%D8%A9-%D8%A7%D9%84%D8%B1%D9%8A%D8%A7%D8%B6-6636357
E15: شقة للإيجار في شارع الأمير عبدالعزيز بن محمد بن عياف, حي الياسمين, مدينة الرياض, منطقة الرياض | F15: 2Bd | G15: Furnished | H15: =80000/12 -> 6666.6667 | I15: https://sa.aqar.fm/%D8%B4%D9%82%D9%82-%D9%84%D9%84%D8%A5%D9%8A%D8%AC%D8%A7%D8%B1/%D8%A7%D9%84%D8%B1%D9%8A%D8%A7%D8%B6/%D8%B4%D9%85%D8%A7%D9%84-%D8%A7%D9%84%D8%B1%D9%8A%D8%A7%D8%B6/%D8%AD%D9%8A-%D8%A7%D9%84%D9%8A%D8%A7%D8%B3%D9%85%D9%8A%D9%86/%D8%B4%D8%A7%D8%B1%D8%B9-%D8%A7%D9%84%D8%A3%D9%85%D9%8A%D8%B1-%D8%B9%D8%A8%D8%AF%D8%A7%D9%84%D8%B9%D8%B2%D9%8A%D8%B2-%D8%A8%D9%86-%D9%85%D8%AD%D9%85%D8%AF-%D8%A8%D9%86-%D8%B9%D9%8A%D8%A7%D9%81-%D8%AD%D9%8A-%D8%A7%D9%84%D9%8A%D8%A7%D8%B3%D9%85%D9%8A%D9%86-%D8%A7%D9%84%D8%B1%D9%8A%D8%A7%D8%B6-6127122
E16: شقة للإيجار في شارع شهيد الدين ثم الوطن عبدالله عبدالرحمن, حي الياسمين, مدينة الرياض, منطقة الرياض | F16: 2Bd | G16: Furnished | H16: 7900 | I16: https://sa.aqar.fm/%D8%B4%D9%82%D9%82-%D9%84%D9%84%D8%A5%D9%8A%D8%AC%D8%A7%D8%B1/%D8%A7%D9%84%D8%B1%D9%8A%D8%A7%D8%B6/%D8%B4%D9%85%D8%A7%D9%84-%D8%A7%D9%84%D8%B1%D9%8A%D8%A7%D8%B6/%D8%AD%D9%8A-%D8%A7%D9%84%D9%8A%D8%A7%D8%B3%D9%85%D9%8A%D9%86/%D8%B4%D8%A7%D8%B1%D8%B9-%D8%B4%D9%87%D9%8A%D8%AF-%D8%A7%D9%84%D8%AF%D9%8A%D9%86-%D8%AB%D9%85-%D8%A7%D9%84%D9%88%D8%B7%D9%86-%D8%B9%D8%A8%D8%AF%D8%A7%D9%84%D9%84%D9%87-%D8%B9%D8%A8%D8%AF%D8%A7%D9%84%D8%B1%D8%AD%D9%85%D9%86-%D8%AD%D9%8A-%D8%A7%D9%84%D9%8A%D8%A7%D8%B3%D9%85%D9%8A%D9%86-%D9%85%D8%AF%D9%8A%D9%86%D8%A9-%D8%A7%D9%84%D8%B1%D9%8A%D8%A7%D8%B6-%D9%85%D9%86%D8%B7%D9%82%D8%A9-%D8%A7%D9%84%D8%B1%D9%8A%D8%A7%D8%B6-6636931
E17: شقة للإيجار في شارع رقم 190, حي الياسمين, مدينة الرياض, منطقة الرياض | F17: 2Bd | G17: Furnished | H17: =100000/12 -> 8333.3333 | I17: https://sa.aqar.fm/%D8%B4%D9%82%D9%82-%D9%84%D9%84%D8%A5%D9%8A%D8%AC%D8%A7%D8%B1/%D8%A7%D9%84%D8%B1%D9%8A%D8%A7%D8%B6/%D8%B4%D9%85%D8%A7%D9%84-%D8%A7%D9%84%D8%B1%D9%8A%D8%A7%D8%B6/%D8%AD%D9%8A-%D8%A7%D9%84%D9%8A%D8%A7%D8%B3%D9%85%D9%8A%D9%86/%D8%B4%D8%A7%D8%B1%D8%B9-%D8%B1%D9%82%D9%85-190-%D8%AD%D9%8A-%D8%A7%D9%84%D9%8A%D8%A7%D8%B3%D9%85%D9%8A%D9%86-%D8%A7%D9%84%D8%B1%D9%8A%D8%A7%D8%B6-%D9%85%D9%86%D8%B7%D9%82%D8%A9-%D8%A7%D9%84%D8%B1%D9%8A%D8%A7%D8%B6-6824861
E18: شقة للإيجار في شارع شارع رقم 163, حي الياسمين, مدينة الرياض, منطقة الرياض | F18: 2Bd | G18: Furnished | H18: =75000/12 -> 6250 | I18: https://sa.aqar.fm/%D8%B4%D9%82%D9%82-%D9%84%D9%84%D8%A5%D9%8A%D8%AC%D8%A7%D8%B1/%D8%A7%D9%84%D8%B1%D9%8A%D8%A7%D8%B6/%D8%B4%D9%85%D8%A7%D9%84-%D8%A7%D9%84%D8%B1%D9%8A%D8%A7%D8%B6/%D8%AD%D9%8A-%D8%A7%D9%84%D9%8A%D8%A7%D8%B3%D9%85%D9%8A%D9%86/%D8%B4%D8%A7%D8%B1%D8%B9-%D8%B1%D9%82%D9%85-163-%D8%AD%D9%8A-%D8%A7%D9%84%D9%86%D8%B1%D8%AC%D8%B3-%D8%A7%D9%84%D8%B1%D9%8A%D8%A7%D8%B6-%D9%85%D9%86%D8%B7%D9%82%D8%A9-%D8%A7%D9%84%D8%B1%D9%8A%D8%A7%D8%B6-6607304
E19: شقة للإيجار في شارع رقم 228, حي الياسمين, مدينة الرياض, منطقة الرياض | F19: 2Bd | G19: Furnished | H19: =85000/12 -> 7083.3333 | I19: https://sa.aqar.fm/%D8%B4%D9%82%D9%82-%D9%84%D9%84%D8%A5%D9%8A%D8%AC%D8%A7%D8%B1/%D8%A7%D9%84%D8%B1%D9%8A%D8%A7%D8%B6/%D8%B4%D9%85%D8%A7%D9%84-%D8%A7%D9%84%D8%B1%D9%8A%D8%A7%D8%B6/%D8%AD%D9%8A-%D8%A7%D9%84%D9%8A%D8%A7%D8%B3%D9%85%D9%8A%D9%86/%D8%B4%D8%A7%D8%B1%D8%B9-%D8%B1%D9%82%D9%85-228-%D8%AD%D9%8A-%D8%A7%D9%84%D9%8A%D8%A7%D8%B3%D9%85%D9%8A%D9%86-%D9%85%D8%AF%D9%8A%D9%86%D8%A9-%D8%A7%D9%84%D8%B1%D9%8A%D8%A7%D8%B6-%D9%85%D9%86%D8%B7%D9%82%D8%A9-%D8%A7%D9%84%D8%B1%D9%8A%D8%A7%D8%B6-6852791
E20: ستاي الياسمين | F20: 2Bd | G20: Furnished | H20: 8990 | I20: https://www.bayut.sa/%D8%A7%D9%84%D8%B9%D9%82%D8%A7%D8%B1/%D8%AA%D9%81%D8%A7%D8%B5%D9%8A%D9%84-87781506.html
E21: حياة عصرية تبدأ من هنا – سكن راقٍ في الماجدية مع ستاي | F21: 2Bd | G21: Furnished | H21: 7900 | I21: https://www.bayut.sa/%D8%A7%D9%84%D8%B9%D9%82%D8%A7%D8%B1/%D8%AA%D9%81%D8%A7%D8%B5%D9%8A%D9%84-87780267.html
E22: شقة للايجار في حي الياسمين، شمال الرياض | F22: 2Bd | G22: Furnished | H22: =80000/12 -> 6666.6667 | I22: https://www.bayut.sa/%D8%A7%D9%84%D8%B9%D9%82%D8%A7%D8%B1/%D8%AA%D9%81%D8%A7%D8%B5%D9%8A%D9%84-87986874.html
E23: شقة مؤثثة جديدة في حي الياسمين | F23: 2Bd | G23: Furnished | H23: =85000/12 -> 7083.3333 | I23: https://www.bayut.sa/%D8%A7%D9%84%D8%B9%D9%82%D8%A7%D8%B1/%D8%AA%D9%81%D8%A7%D8%B5%D9%8A%D9%84-88088914.html
E24: شقة للإيجار في الياسمين، الرياض | F24: 2Bd | G24: Furnished | H24: =65000/12 -> 5416.6667 | I24: https://www.bayut.sa/%D8%A7%D9%84%D8%B9%D9%82%D8%A7%D8%B1/%D8%AA%D9%81%D8%A7%D8%B5%D9%8A%D9%84-88009676.html
E25: شقة من غرفتين للإيجار في الياسمين، الرياض | F25: 2Bd | G25: Furnished | H25: =80000/12 -> 6666.6667 | I25: https://www.bayut.sa/%D8%A7%D9%84%D8%B9%D9%82%D8%A7%D8%B1/%D8%AA%D9%81%D8%A7%D8%B5%D9%8A%D9%84-88054713.html
E26: شقه #8 | F26: 2Bd | G26: Furnished | H26: =90000/12 -> 7500 | I26: https://www.bayut.sa/%D8%A7%D9%84%D8%B9%D9%82%D8%A7%D8%B1/%D8%AA%D9%81%D8%A7%D8%B5%D9%8A%D9%84-87948276.html

Sheet LTR-3BR-Master-Data
A1: Unit Type | B1: Average | C1: Minimum | D1: Maximum
A2: 3BR | B2: =(D2+C2)/2 -> 12395.833 | C2: =B3 -> 9791.6667 | D2: =MAX($H$11:$H$26) -> 15000 | E2: Alternative Method
A3: 3BR | B3: =AVERAGE($H$11:$H$26) -> 9791.6667 | C3: =ROUND(AVERAGE($H$11:$H$26) -_xlfn.T.INV.2T(0.05, COUNT($H$11:$H$26)-1) * (_xlfn.STDEV.S($H$11:$H$26) / SQRT(COUNT($H$11:$H$26))),0) -> 8617 | D3: 10500 | E3: Ordinary Method
A9: Metrics
A10: ST.Deviation | B10: =STDEV($H$11:$H$26) -> 2204.7928 | E10: Unit Name | F10: Type | G10: Status | H10: LTR Price | I10: Link
A11: Median | B11: =MEDIAN($H$11:$H$26) -> 9375 | E11: سكن عائلي متكامل | شقة 3 غرف - الياسمين | F11: 3BR | G11: Furnished | H11: =100000/12 -> 8333.3333 | I11: https://www.bayut.sa/%D8%A7%D9%84%D8%B9%D9%82%D8%A7%D8%B1/%D8%AA%D9%81%D8%A7%D8%B5%D9%8A%D9%84-88112053.html
A12: Average | B12: =round(AVERAGE($H$11:$H$26),0) -> 9792 | E12: شقة مؤثثة بحي الياسمين | F12: 3BR | G12: Furnished | H12: =120000/12 -> 10000 | I12: https://www.bayut.sa/%D8%A7%D9%84%D8%B9%D9%82%D8%A7%D8%B1/%D8%AA%D9%81%D8%A7%D8%B5%D9%8A%D9%84-88051341.html
A13: Minimum | B13: =MIN(H11:H26) -> 6666.6667 | E13: شقق 3 غرف نوم للإيجار الشهري & السنوي في الياسمين، الرياض | F13: 3BR | G13: Furnished | H13: =155000/12 -> 12916.667 | I13: https://www.bayut.sa/%D8%A7%D9%84%D8%B9%D9%82%D8%A7%D8%B1/%D8%AA%D9%81%D8%A7%D8%B5%D9%8A%D9%84-88122226.html
A14: Maxim | B14: =MAX(H11:H26) -> 15000 | E14: شقة 3 غرف نوم، مرافق متكاملة | حي الياسمين - ساتل | F14: 3BR | G14: Furnished | H14: =100000/12 -> 8333.3333 | I14: https://www.bayut.sa/%D8%A7%D9%84%D8%B9%D9%82%D8%A7%D8%B1/%D8%AA%D9%81%D8%A7%D8%B5%D9%8A%D9%84-88112063.html
E15: شقة للايجار في الماجدية حي الياسمين | F15: 3BR | G15: Furnished | H15: 10000 | I15: https://www.bayut.sa/%D8%A7%D9%84%D8%B9%D9%82%D8%A7%D8%B1/%D8%AA%D9%81%D8%A7%D8%B5%D9%8A%D9%84-88105658.html
E16: شقة مكونة من 3 غرف نوم للإيجار في الياقوت، الرياض | F16: 3BR | G16: Furnished | H16: =160000/12 -> 13333.333 | I16: https://www.bayut.sa/%D8%A7%D9%84%D8%B9%D9%82%D8%A7%D8%B1/%D8%AA%D9%81%D8%A7%D8%B5%D9%8A%D9%84-87997094.html
E17: شقة ثلاث غرف نوم و مجلس مفروشة | F17: 3BR | G17: Furnished | H17: 10000 | I17: https://www.bayut.sa/%D8%A7%D9%84%D8%B9%D9%82%D8%A7%D8%B1/%D8%AA%D9%81%D8%A7%D8%B5%D9%8A%D9%84-88105258.html
E18: شقق 3 غرف نوم للإيجار الشهري & السنوي في الياسمين، الرياض | F18: 3BR | G18: Furnished | H18: 15000 | I18: https://www.bayut.sa/%D8%A7%D9%84%D8%B9%D9%82%D8%A7%D8%B1/%D8%AA%D9%81%D8%A7%D8%B5%D9%8A%D9%84-88122229.html
E19: شقة مؤثثة للإيجار في حي الياسمين – الرياض | F19: 3BR | G19: Furnished | H19: =115000/12 -> 9583.3333 | I19: https://www.bayut.sa/%D8%A7%D9%84%D8%B9%D9%82%D8%A7%D8%B1/%D8%AA%D9%81%D8%A7%D8%B5%D9%8A%D9%84-88125765.html
E20: للايجار شقة مميزة في حي الياسمين | F20: 3BR | G20: Furnished | H20: =80000/12 -> 6666.6667 | I20: https://www.bayut.sa/%D8%A7%D9%84%D8%B9%D9%82%D8%A7%D8%B1/%D8%AA%D9%81%D8%A7%D8%B5%D9%8A%D9%84-88100123.html
E21: شقة مفروشة في حي الياسمين الماجدية9 | F21: 3BR | G21: Furnished | H21: =120000/12 -> 10000 | I21: https://www.bayut.sa/%D8%A7%D9%84%D8%B9%D9%82%D8%A7%D8%B1/%D8%AA%D9%81%D8%A7%D8%B5%D9%8A%D9%84-88039158.html
E22: شقة مكونة من 3 غرف للإيجار في الياسمين | F22: 3BR | G22: Furnished | H22: =100000/12 -> 8333.3333 | I22: https://www.bayut.sa/%D8%A7%D9%84%D8%B9%D9%82%D8%A7%D8%B1/%D8%AA%D9%81%D8%A7%D8%B5%D9%8A%D9%84-87999566.html
E23: شقة للإيجار في الياسمين، الرياض | F23: 3BR | G23: Furnished | H23: =110000/12 -> 9166.6667 | I23: https://www.bayut.sa/%D8%A7%D9%84%D8%B9%D9%82%D8%A7%D8%B1/%D8%AA%D9%81%D8%A7%D8%B5%D9%8A%D9%84-88062332.html
E24: شقة للايجار في الياسمين , الرياض | F24: 3BR | G24: Furnished | H24: =105000/12 -> 8750 | I24: https://www.bayut.sa/%D8%A7%D9%84%D8%B9%D9%82%D8%A7%D8%B1/%D8%AA%D9%81%D8%A7%D8%B5%D9%8A%D9%84-87908659.html
E25: شقة مؤثثة 3 غرف نوم للإيجار | F25: 3BR | G25: Furnished | H25: =100000/12 -> 8333.3333 | I25: https://www.bayut.sa/%D8%A7%D9%84%D8%B9%D9%82%D8%A7%D8%B1/%D8%AA%D9%81%D8%A7%D8%B5%D9%8A%D9%84-87948643.html
E26: شقه #7 | F26: 3BR | G26: Furnished | H26: =95000/12 -> 7916.6667 | I26: https://www.bayut.sa/%D8%A7%D9%84%D8%B9%D9%82%D8%A7%D8%B1/%D8%AA%D9%81%D8%A7%D8%B5%D9%8A%D9%84-87948271.html

Sheet LTR-Regular Financial Study
H6: Best Case | I6: Base Case | J6: Worst Case | K6: Type | L6: Unit
H7: ='Ltr-1BR-Master-Data'!$D$3 -> 4900 | I7: ='Ltr-1BR-Master-Data'!$B$3 -> 4500 | J7: ='Ltr-1BR-Master-Data'!$C$3 -> 4200 | K7: 1Bd | L7: {=SEQUENCE(54,1,1,1)} -> 1
H8: ='Ltr-1BR-Master-Data'!$D$3 -> 4900 | I8: ='Ltr-1BR-Master-Data'!$B$3 -> 4500 | J8: ='Ltr-1BR-Master-Data'!$C$3 -> 4200 | K8: 1Bd | L8: 2
H9: ='Ltr-1BR-Master-Data'!$D$3 -> 4900 | I9: ='Ltr-1BR-Master-Data'!$B$3 -> 4500 | J9: ='Ltr-1BR-Master-Data'!$C$3 -> 4200 | K9: 1Bd | L9: 3
H10: ='Ltr-1BR-Master-Data'!$D$3 -> 4900 | I10: ='Ltr-1BR-Master-Data'!$B$3 -> 4500 | J10: ='Ltr-1BR-Master-Data'!$C$3 -> 4200 | K10: 1Bd | L10: 4
H11: ='Ltr-1BR-Master-Data'!$D$3 -> 4900 | I11: ='Ltr-1BR-Master-Data'!$B$3 -> 4500 | J11: ='Ltr-1BR-Master-Data'!$C$3 -> 4200 | K11: 1Bd | L11: 5
H12: ='Ltr-1BR-Master-Data'!$D$3 -> 4900 | I12: ='Ltr-1BR-Master-Data'!$B$3 -> 4500 | J12: ='Ltr-1BR-Master-Data'!$C$3 -> 4200 | K12: 1Bd | L12: 6
H13: ='Ltr-1BR-Master-Data'!$D$3 -> 4900 | I13: ='Ltr-1BR-Master-Data'!$B$3 -> 4500 | J13: ='Ltr-1BR-Master-Data'!$C$3 -> 4200 | K13: 1Bd | L13: 7
H14: ='Ltr-1BR-Master-Data'!$D$3 -> 4900 | I14: ='Ltr-1BR-Master-Data'!$B$3 -> 4500 | J14: ='Ltr-1BR-Master-Data'!$C$3 -> 4200 | K14: 1Bd | L14: 8
H15: ='Ltr-1BR-Master-Data'!$D$3 -> 4900 | I15: ='Ltr-1BR-Master-Data'!$B$3 -> 4500 | J15: ='Ltr-1BR-Master-Data'!$C$3 -> 4200 | K15: 1Bd | L15: 9
H16: ='Ltr-1BR-Master-Data'!$D$3 -> 4900 | I16: ='Ltr-1BR-Master-Data'!$B$3 -> 4500 | J16: ='Ltr-1BR-Master-Data'!$C$3 -> 4200 | K16: 1Bd | L16: 10
H17: ='Ltr-1BR-Master-Data'!$D$3 -> 4900 | I17: ='Ltr-1BR-Master-Data'!$B$3 -> 4500 | J17: ='Ltr-1BR-Master-Data'!$C$3 -> 4200 | K17: 1Bd | L17: 11
H18: ='Ltr-1BR-Master-Data'!$D$3 -> 4900 | I18: ='Ltr-1BR-Master-Data'!$B$3 -> 4500 | J18: ='Ltr-1BR-Master-Data'!$C$3 -> 4200 | K18: 1Bd | L18: 12
H19: ='Ltr-1BR-Master-Data'!$D$3 -> 4900 | I19: ='Ltr-1BR-Master-Data'!$B$3 -> 4500 | J19: ='Ltr-1BR-Master-Data'!$C$3 -> 4200 | K19: 1Bd | L19: 13
... H60: ='Ltr-1BR-Master-Data'!$D$3 -> 4900 | I60: ='Ltr-1BR-Master-Data'!$B$3 -> 4500 | J60: ='Ltr-1BR-Master-Data'!$C$3 -> 4200 | K60: 1Bd | L60: 54
H61: ='LTR-2BR-Master-Data'!$D$3 -> 8796 | I61: ='LTR-2BR-Master-Data'!$B$3 -> 7762.9167 | J61: ='LTR-2BR-Master-Data'!$C$3 -> 6730 | K61: 2Bd | L61: {=SEQUENCE(29,1,1,1)} -> 1
H62: ='LTR-2BR-Master-Data'!$D$3 -> 8796 | I62: ='LTR-2BR-Master-Data'!$B$3 -> 7762.9167 | J62: ='LTR-2BR-Master-Data'!$C$3 -> 6730 | K62: 2Bd | L62: 2
H63: ='LTR-2BR-Master-Data'!$D$3 -> 8796 | I63: ='LTR-2BR-Master-Data'!$B$3 -> 7762.9167 | J63: ='LTR-2BR-Master-Data'!$C$3 -> 6730 | K63: 2Bd | L63: 3
H64: ='LTR-2BR-Master-Data'!$D$3 -> 8796 | I64: ='LTR-2BR-Master-Data'!$B$3 -> 7762.9167 | J64: ='LTR-2BR-Master-Data'!$C$3 -> 6730 | K64: 2Bd | L64: 4
H65: ='LTR-2BR-Master-Data'!$D$3 -> 8796 | I65: ='LTR-2BR-Master-Data'!$B$3 -> 7762.9167 | J65: ='LTR-2BR-Master-Data'!$C$3 -> 6730 | K65: 2Bd | L65: 5
H66: ='LTR-2BR-Master-Data'!$D$3 -> 8796 | I66: ='LTR-2BR-Master-Data'!$B$3 -> 7762.9167 | J66: ='LTR-2BR-Master-Data'!$C$3 -> 6730 | K66: 2Bd | L66: 6
H67: ='LTR-2BR-Master-Data'!$D$3 -> 8796 | I67: ='LTR-2BR-Master-Data'!$B$3 -> 7762.9167 | J67: ='LTR-2BR-Master-Data'!$C$3 -> 6730 | K67: 2Bd | L67: 7
H68: ='LTR-2BR-Master-Data'!$D$3 -> 8796 | I68: ='LTR-2BR-Master-Data'!$B$3 -> 7762.9167 | J68: ='LTR-2BR-Master-Data'!$C$3 -> 6730 | K68: 2Bd | L68: 8
H69: ='LTR-2BR-Master-Data'!$D$3 -> 8796 | I69: ='LTR-2BR-Master-Data'!$B$3 -> 7762.9167 | J69: ='LTR-2BR-Master-Data'!$C$3 -> 6730 | K69: 2Bd | L69: 9
H70: ='LTR-2BR-Master-Data'!$D$3 -> 8796 | I70: ='LTR-2BR-Master-Data'!$B$3 -> 7762.9167 | J70: ='LTR-2BR-Master-Data'!$C$3 -> 6730 | K70: 2Bd | L70: 10
H71: ='LTR-2BR-Master-Data'!$D$3 -> 8796 | I71: ='LTR-2BR-Master-Data'!$B$3 -> 7762.9167 | J71: ='LTR-2BR-Master-Data'!$C$3 -> 6730 | K71: 2Bd | L71: 11
H72: ='LTR-2BR-Master-Data'!$D$3 -> 8796 | I72: ='LTR-2BR-Master-Data'!$B$3 -> 7762.9167 | J72: ='LTR-2BR-Master-Data'!$C$3 -> 6730 | K72: 2Bd | L72: 12
H73: ='LTR-2BR-Master-Data'!$D$3 -> 8796 | I73: ='LTR-2BR-Master-Data'!$B$3 -> 7762.9167 | J73: ='LTR-2BR-Master-Data'!$C$3 -> 6730 | K73: 2Bd | L73: 13
... H89: ='LTR-2BR-Master-Data'!$D$3 -> 8796 | I89: ='LTR-2BR-Master-Data'!$B$3 -> 7762.9167 | J89: ='LTR-2BR-Master-Data'!$C$3 -> 6730 | K89: 2Bd | L89: 29
H90: ='LTR-3BR-Master-Data'!$D$3 -> 10500 | I90: ='LTR-3BR-Master-Data'!$B$3 -> 9791.6667 | J90: ='LTR-3BR-Master-Data'!$C$3 -> 8617 | K90: 3BR | L90: 1
H91: ='LTR-3BR-Master-Data'!$D$3 -> 10500 | I91: ='LTR-3BR-Master-Data'!$B$3 -> 9791.6667 | J91: ='LTR-3BR-Master-Data'!$C$3 -> 8617 | K91: 3BR | L91: 2
H92: ='LTR-3BR-Master-Data'!$D$3 -> 10500 | I92: ='LTR-3BR-Master-Data'!$B$3 -> 9791.6667 | J92: ='LTR-3BR-Master-Data'!$C$3 -> 8617 | K92: 3BR | L92: 3
H94: =SUM(H$7:H$92)*12 -> 6614208 | I94: =SUM(I$7:I$92)*12 -> 5969995 | J94: =SUM(J$7:J$92)*12 -> 5373852 | K94: Total

Sheet High Post LTR-Cleaning
A1: Unit Type | B1: Average | C1: Minimum | D1: Maximum
A2: 2Bd | B2: 13295.54 | C2: 10542.08 | D2: 16049
A3: 2Bd | B3: 10542.08 | C3: 9741 | D3: 11343
A4: =STDEV(E11:E64) -> #DIV/0! | B4: Standard Deviaton
A5: =AVERAGE(E11:E64) -> #DIV/0! | B5: average
A6: =MEDIAN(E11:E64) -> #NUM! | B6: median
A9: High
A10: Unit Name | B10: Type | C10: Status | D10: Monthly Price | E10: After Airbnb Discount | F10: Priority | G10: Link
A11: =IFERROR(__xludf.DUMMYFUNCTION("FILTER('STR-1BR-Master-Data'!E11:I40,#REF!=#REF!,'STR-1BR-Master-Data'!G11:G40='STR-1BR-Master-Data'!G22)"),"#N/A") -> #N/A

Sheet Medium Post-Cleaning
A1: Unit Type | B1: Average | C1: Minimum | D1: Maximum
A2: 2Bd | B2: =(D2+C2)/2 -> #DIV/0! | C2: =AVERAGE($E$11:$E$18) -> #DIV/0! | D2: =MAX($E$11:$E$18) -> 0 | E2: Alternate Method
A3: 2Bd | B3: =AVERAGE($E$11:$E$18) -> #DIV/0! | C3: =ROUND(AVERAGE($E$11:$E$18) -_xlfn.T.INV.2T(0.05, COUNT($E$11:$E$18)-1) * (_xlfn.STDEV.S($E$11:$E$18) / SQRT(COUNT($E$11:$E$18))),0) -> #DIV/0! | D3: =round(AVERAGE($E$11:$E$18) + _xlfn.T.INV.2T(0.05, COUNT($E$11:$E$18)-1) * (_xlfn.STDEV.S($E$11:$E$18) / SQRT(COUNT($E$11:$E$18))) ,0) -> #DIV/0! | E3: Ordinary Method
A4: =STDEV(E11:E45) -> #DIV/0! | B4: Standard Deviaton
A5: =AVERAGE(E11:E45) -> #DIV/0! | B5: average
A6: =MEDIAN(E11:E45) -> #NUM! | B6: median
A9: Medium
A10: Unit Name | B10: Type | C10: Status | D10: Monthly Price | E10: After Airbnb Discount | F10: Priority | G10: Link
A11: =IFERROR(__xludf.DUMMYFUNCTION("FILTER('STR-1BR-Master-Data'!E11:I40,#REF!=#REF!)"),"#N/A") -> #N/A

Sheet  LTR Financial Study
E5: No. of units | F5: Type
E6: 5 | F6: 3BR | H6: Best Case | I6: Base Case | J6: Worst Case | K6: Type | L6: Unit
E7: 4 | F7: 2BR | H7: ='High Post LTR-Cleaning'!$D$3 -> 11343 | I7: ='STR-1BR-Master-Data'!$B$3 -> 406.29545 | J7: ='STR-1BR-Master-Data'!$C$3 -> 363 | K7: 3BR | L7: {=SEQUENCE(9,1,1,1)} -> 1
H8: ='High Post LTR-Cleaning'!$D$3 -> 11343 | I8: ='STR-1BR-Master-Data'!$B$3 -> 406.29545 | J8: ='STR-1BR-Master-Data'!$C$3 -> 363 | K8: 3BR | L8: 2
H9: ='High Post LTR-Cleaning'!$D$3 -> 11343 | I9: ='STR-1BR-Master-Data'!$B$3 -> 406.29545 | J9: ='STR-1BR-Master-Data'!$C$3 -> 363 | K9: 2BR | L9: 3
H10: ='High Post LTR-Cleaning'!$D$3 -> 11343 | I10: ='STR-1BR-Master-Data'!$B$3 -> 406.29545 | J10: ='STR-1BR-Master-Data'!$C$3 -> 363 | K10: 2BR | L10: 4
H11: ='High Post LTR-Cleaning'!$D$3 -> 11343 | I11: ='STR-1BR-Master-Data'!$B$3 -> 406.29545 | J11: ='STR-1BR-Master-Data'!$C$3 -> 363 | K11: 3BR | L11: 5
H12: ='High Post LTR-Cleaning'!$D$3 -> 11343 | I12: ='STR-1BR-Master-Data'!$B$3 -> 406.29545 | J12: ='STR-1BR-Master-Data'!$C$3 -> 363 | K12: 3BR | L12: 6
H13: ='High Post LTR-Cleaning'!$D$3 -> 11343 | I13: ='STR-1BR-Master-Data'!$B$3 -> 406.29545 | J13: ='STR-1BR-Master-Data'!$C$3 -> 363 | K13: 3BR | L13: 7
H14: ='High Post LTR-Cleaning'!$D$3 -> 11343 | I14: ='STR-1BR-Master-Data'!$B$3 -> 406.29545 | J14: ='STR-1BR-Master-Data'!$C$3 -> 363 | K14: 2BR | L14: 8
H15: ='High Post LTR-Cleaning'!$D$3 -> 11343 | I15: ='STR-1BR-Master-Data'!$B$3 -> 406.29545 | J15: ='STR-1BR-Master-Data'!$C$3 -> 363 | K15: 2BR | L15: 9
H17: =SUM(H7:H15)*12 -> 1225044 | I17: =SUM(I7:I15)*12 -> 43879.909 | J17: =SUM(J7:J15)*12 -> 39204 | K17: Total

Sheet LTR Study Summary
L5: No. of units | M5: Type
L6: 5 | M6: 3BR
L7: 4 | M7: 2BR
H10: Financial Study
F11: Worst Case | L11: Base Case | Q11: Best Case | W11: Scenarios
F12: =' LTR Financial Study'!J17 -> 39204 | L12: =' LTR Financial Study'!I17 -> 43879.909 | Q12: =' LTR Financial Study'!H17 -> 1225044 | W12: Revenue at 100% occupancy
F13: 0.5 | G13: 0.6 | H13: 0.7 | I13: 0.8 | J13: 0.9 | L13: 0.5 | M13: 0.6 | N13: 0.7 | O13: 0.8 | P13: 0.9 | Q13: 0.5 | R13: 0.6 | S13: 0.7 | T13: 0.8 | U13: 0.9 | W13: Varying occupancy scenario
F14: =$F$12*F13 -> 19602 | G14: =$F$12*G13 -> 23522.4 | H14: =$F$12*H13 -> 27442.8 | I14: =$F$12*I13 -> 31363.2 | J14: =$F$12*J13 -> 35283.6 | L14: =$L$12*L13 -> 21939.955 | M14: =$L$12*M13 -> 26327.945 | N14: =$L$12*N13 -> 30715.936 | O14: =$L$12*O13 -> 35103.927 | P14: =$L$12*P13 -> 39491.918 | Q14: =$Q$12*Q13 -> 612522 | R14: =$Q$12*R13 -> 735026.4 | S14: =$Q$12*S13 -> 857530.8 | T14: =$Q$12*T13 -> 980035.2 | U14: =$Q$12*U13 -> 1102539.6 | W14: Revenue pre deductions
F15: =F14*(1-$W$16) -> 15681.6 | G15: =G14*(1-$W$16) -> 18817.92 | H15: =H14*(1-$W$16) -> 21954.24 | I15: =I14*(1-$W$16) -> 25090.56 | J15: =J14*(1-$W$16) -> 28226.88 | L15: =L14*(1-$W$16) -> 17551.964 | M15: =M14*(1-$W$16) -> 21062.356 | N15: =N14*(1-$W$16) -> 24572.749 | O15: =O14*(1-$W$16) -> 28083.142 | P15: =P14*(1-$W$16) -> 31593.535 | Q15: =Q14*(1-$W$16) -> 490017.6 | R15: =R14*(1-$W$16) -> 588021.12 | S15: =S14*(1-$W$16) -> 686024.64 | ... U15: =U14*(1-$W$16) -> 882031.68 | W15: Net Revenue After deducting operaror fees
W16: 0.2
F19: =F15/SUM($L$6:$L$7) -> 1742.4 | G19: =G15/SUM($L$6:$L$7) -> 2090.88 | H19: =H15/SUM($L$6:$L$7) -> 2439.36 | I19: =I15/SUM($L$6:$L$7) -> 2787.84 | J19: =J15/SUM($L$6:$L$7) -> 3136.32 | L19: =L15/SUM($L$6:$L$7) -> 1950.2182 | M19: =M15/SUM($L$6:$L$7) -> 2340.2618 | N19: =N15/SUM($L$6:$L$7) -> 2730.3055 | O19: =O15/SUM($L$6:$L$7) -> 3120.3491 | P19: =P15/SUM($L$6:$L$7) -> 3510.3927 | Q19: =Q15/SUM($L$6:$L$7) -> 54446.4 | R19: =R15/SUM($L$6:$L$7) -> 65335.68 | S19: =S15/SUM($L$6:$L$7) -> 76224.96 | ... U19: =U15/SUM($L$6:$L$7) -> 98003.52 | W19: Annual Revenue Per Unit
G20: =G14-#REF! -> #REF! | H20: =H14-#REF! -> #REF! | I20: =I14-#REF! -> #REF! | J20: =J14-#REF! -> #REF! | M20: =M14-#REF! -> #REF! | N20: =N14-#REF! -> #REF! | O20: =O14-#REF! -> #REF! | P20: =P14-#REF! -> #REF! | R20: =R14-#REF! -> #REF! | S20: =S14-#REF! -> #REF! | T20: =T14-#REF! -> #REF! | U20: =U14-#REF! -> #REF! | W20: Mathwa Gross Annual Commision
G21: =G20/18 -> #REF! | H21: =H20/18 -> #REF! | I21: =I20/18 -> #REF! | J21: =J20/18 -> #REF! | M21: =M20/18 -> #REF! | N21: =N20/18 -> #REF! | O21: =O20/18 -> #REF! | P21: =P20/18 -> #REF! | R21: =R20/18 -> #REF! | S21: =S20/18 -> #REF! | T21: =T20/18 -> #REF! | U21: =U20/18 -> #REF! | W21: Annual Commission per Unit
G22: =G21/' LTR Financial Study'!$I$7 -> #REF! | H22: =H21/' LTR Financial Study'!$I$7 -> #REF! | I22: =I21/' LTR Financial Study'!$I$7 -> #REF! | J22: =J21/' LTR Financial Study'!$I$7 -> #REF! | M22: =M21/#REF! -> #REF! | N22: =N21/#REF! -> #REF! | O22: =O21/#REF! -> #REF! | P22: =P21/#REF! -> #REF! | R22: =R21/' LTR Financial Study'!$J$7 -> #REF! | S22: =S21/' LTR Financial Study'!$J$7 -> #REF! | T22: =T21/' LTR Financial Study'!$J$7 -> #REF! | U22: =U21/' LTR Financial Study'!$J$7 -> #REF! | W22: Commission-To-Rent Ratio
F23: =F19/12 -> 145.2 | G23: =G19/12 -> 174.24 | H23: =H19/12 -> 203.28 | I23: =I19/12 -> 232.32 | J23: =J19/12 -> 261.36 | L23: =L19/12 -> 162.51818 | M23: =M19/12 -> 195.02182 | N23: =N19/12 -> 227.52545 | O23: =O19/12 -> 260.02909 | P23: =P19/12 -> 292.53273 | Q23: =Q19/12 -> 4537.2 | R23: =R19/12 -> 5444.64 | S23: =S19/12 -> 6352.08 | ... U23: =U19/12 -> 8166.96 | W23: Monthly Revenue Per Unit
H28: =' LTR Financial Study'!C17

Sheet Hybrid Financial Study
A4: Assumptions
A5: We will Assume that we will have from October to February
A6: STR Model | B6: and the rest will be LTR
E7: No. of units | F7: Type
A8: Type | B8: WA | E8: 5 | F8: 3BR | H8: Best Case | I8: Base Case | J8: Worst Case | K8: Type | L8: Unit
A9: STR | B9: =5/12 -> 0.41666667 | E9: 4 | F9: 2BR | H9: =('STR-Regular Financial Study'!$H$7*$B$9)+(' LTR Financial Study'!$H$7*$B$10) -> 12229.25 | I9: =('STR-Regular Financial Study'!$I$7*$B$9)+(' LTR Financial Study'!$I$7*$B$10) -> 5315.6989 | J9: =('STR-Regular Financial Study'!$J$7*$B$9)+(' LTR Financial Study'!$J$7*$B$10) -> 4749.25 | K9: 2BR | L9: {=SEQUENCE(9,1,1,1)} -> 1
A10: LTR | B10: =1-B9 -> 0.58333333 | H10: =('STR-Regular Financial Study'!$H$7*$B$9)+(' LTR Financial Study'!$H$7*$B$10) -> 12229.25 | I10: =('STR-Regular Financial Study'!$I$7*$B$9)+(' LTR Financial Study'!$I$7*$B$10) -> 5315.6989 | J10: =('STR-Regular Financial Study'!$J$7*$B$9)+(' LTR Financial Study'!$J$7*$B$10) -> 4749.25 | K10: 2BR | L10: 2
H11: =('STR-Regular Financial Study'!$H$7*$B$9)+(' LTR Financial Study'!$H$7*$B$10) -> 12229.25 | I11: =('STR-Regular Financial Study'!$I$7*$B$9)+(' LTR Financial Study'!$I$7*$B$10) -> 5315.6989 | J11: =('STR-Regular Financial Study'!$J$7*$B$9)+(' LTR Financial Study'!$J$7*$B$10) -> 4749.25 | K11: 2BR | L11: 3
H12: =('STR-Regular Financial Study'!$H$7*$B$9)+(' LTR Financial Study'!$H$7*$B$10) -> 12229.25 | I12: =('STR-Regular Financial Study'!$I$7*$B$9)+(' LTR Financial Study'!$I$7*$B$10) -> 5315.6989 | J12: =('STR-Regular Financial Study'!$J$7*$B$9)+(' LTR Financial Study'!$J$7*$B$10) -> 4749.25 | K12: 2BR | L12: 4
H13: =('STR-Regular Financial Study'!$H$7*$B$9)+(' LTR Financial Study'!$H$7*$B$10) -> 12229.25 | I13: =('STR-Regular Financial Study'!$I$7*$B$9)+(' LTR Financial Study'!$I$7*$B$10) -> 5315.6989 | J13: =('STR-Regular Financial Study'!$J$7*$B$9)+(' LTR Financial Study'!$J$7*$B$10) -> 4749.25 | K13: 2BR | L13: 5
H14: =('STR-Regular Financial Study'!$H$7*$B$9)+(' LTR Financial Study'!$H$7*$B$10) -> 12229.25 | I14: =('STR-Regular Financial Study'!$I$7*$B$9)+(' LTR Financial Study'!$I$7*$B$10) -> 5315.6989 | J14: =('STR-Regular Financial Study'!$J$7*$B$9)+(' LTR Financial Study'!$J$7*$B$10) -> 4749.25 | K14: 2BR | L14: 6
H15: =('STR-Regular Financial Study'!$H$7*$B$9)+(' LTR Financial Study'!$H$7*$B$10) -> 12229.25 | I15: =('STR-Regular Financial Study'!$I$7*$B$9)+(' LTR Financial Study'!$I$7*$B$10) -> 5315.6989 | J15: =('STR-Regular Financial Study'!$J$7*$B$9)+(' LTR Financial Study'!$J$7*$B$10) -> 4749.25 | K15: 2BR | L15: 7
H16: =('STR-Regular Financial Study'!$H$7*$B$9)+(' LTR Financial Study'!$H$7*$B$10) -> 12229.25 | I16: =('STR-Regular Financial Study'!$I$7*$B$9)+(' LTR Financial Study'!$I$7*$B$10) -> 5315.6989 | J16: =('STR-Regular Financial Study'!$J$7*$B$9)+(' LTR Financial Study'!$J$7*$B$10) -> 4749.25 | K16: 2BR | L16: 8
H17: =('STR-Regular Financial Study'!$H$7*$B$9)+(' LTR Financial Study'!$H$7*$B$10) -> 12229.25 | I17: =('STR-Regular Financial Study'!$I$7*$B$9)+(' LTR Financial Study'!$I$7*$B$10) -> 5315.6989 | J17: =('STR-Regular Financial Study'!$J$7*$B$9)+(' LTR Financial Study'!$J$7*$B$10) -> 4749.25 | K17: 2BR | L17: 9
C19: =SUM(C9:C17)*12 -> 0 | H19: =SUM(H9:H17)*12 -> 1320759 | I19: =SUM(I9:I17)*12 -> 574095.48 | J19: =SUM(J9:J17)*12 -> 512919 | K19: Total

Sheet STR Study Summary
O5: No. of units | P5: Type
O6: 1 | P6: 1Bd
L10: Financial Study - Malqa
F11: Worst Case | L11: Base Case | R11: Best Case | X11: Scenarios
F12: ='STR Financial Study'!J30 -> #REF! | L12: ='STR Financial Study'!I30 -> #REF! | R12: ='STR Financial Study'!H30 -> #REF! | X12: Revenue at 100% occupancy
F13: 0.4 | G13: 0.5 | H13: 0.6 | I13: 0.7 | J13: 0.8 | K13: 0.9 | L13: 0.4 | M13: 0.5 | N13: 0.6 | O13: 0.7 | P13: 0.8 | Q13: 0.9 | R13: 0.4 | S13: 0.5 | T13: 0.6 | U13: 0.7 | V13: 0.8 | W13: 0.9 | X13: Varying occupancy scenario
F14: =F12*F13 -> #REF! | G14: =F12*G13 -> #REF! | H14: =F12*H13 -> #REF! | I14: =F12*I13 -> #REF! | J14: =F12*J13 -> #REF! | K14: =F12*K13 -> #REF! | L14: =L12*L13 -> #REF! | M14: =L12*M13 -> #REF! | N14: =L12*N13 -> #REF! | O14: =L12*O13 -> #REF! | P14: =L12*P13 -> #REF! | Q14: =L12*Q13 -> #REF! | R14: =R12*R13 -> #REF! | S14: =R12*S13 -> #REF! | T14: =R12*T13 -> #REF! | U14: =R12*U13 -> #REF! | V14: =R12*V13 -> #REF! | W14: =R12*W13 -> #REF! | X14: Net revenue before deducting Mathwaa share
F15: =F14*(1-$X$16) -> #REF! | G15: =G14*(1-$X$16) -> #REF! | H15: =H14*(1-$X$16) -> #REF! | I15: =I14*(1-$X$16) -> #REF! | J15: =J14*(1-$X$16) -> #REF! | K15: =K14*(1-$X$16) -> #REF! | L15: =L14*(1-$X$16) -> #REF! | M15: =M14*(1-$X$16) -> #REF! | ... W15: =W14*(1-$X$16) -> #REF! | X15: Net revenue after deducting Mathwaa share
X16: 0.15

Sheet LTR Regular Study Summary
L5: No. of units | M5: Type
L6: =COUNTA('STR-Regular Financial Study'!L7:L60) -> 54 | M6: 1Bd
L7: =COUNTA('STR-Regular Financial Study'!L61:L89) -> 29 | M7: 2Bd
L8: =3 -> 3 | M8: 3BR
F10: Financial Study - Leora
F11: Worst Case | L11: Base Case | Q11: Best Case | W11: Scenarios
F12: ='LTR-Regular Financial Study'!J94 -> 5373852 | L12: ='LTR-Regular Financial Study'!I94 -> 5969995 | Q12: ='LTR-Regular Financial Study'!H94 -> 6614208 | W12: Revenue at 100% occupancy
F13: 0.5 | G13: 0.6 | H13: 0.7 | I13: 0.8 | J13: 0.9 | L13: 0.5 | M13: 0.6 | N13: 0.7 | O13: 0.8 | P13: 0.9 | Q13: 0.5 | R13: 0.6 | S13: 0.7 | T13: 0.8 | U13: 0.9 | W13: Varying occupancy scenario
F14: =$F$12*F13 -> 2686926 | G14: =$F$12*G13 -> 3224311.2 | H14: =$F$12*H13 -> 3761696.4 | I14: =$F$12*I13 -> 4299081.6 | J14: =$F$12*J13 -> 4836466.8 | L14: =$L$12*L13 -> 2984997.5 | M14: =$L$12*M13 -> 3581997 | N14: =$L$12*N13 -> 4178996.5 | O14: =$L$12*O13 -> 4775996 | P14: =$L$12*P13 -> 5372995.5 | Q14: =$Q$12*Q13 -> 3307104 | R14: =$Q$12*R13 -> 3968524.8 | S14: =$Q$12*S13 -> 4629945.6 | T14: =$Q$12*T13 -> 5291366.4 | U14: =$Q$12*U13 -> 5952787.2 | W14: Revenue pre deductions
F15: =F14*(1-$W$16) -> 2283887.1 | G15: =G14*(1-$W$16) -> 2740664.5 | H15: =H14*(1-$W$16) -> 3197441.9 | I15: =I14*(1-$W$16) -> 3654219.4 | J15: =J14*(1-$W$16) -> 4110996.8 | L15: =L14*(1-$W$16) -> 2537247.9 | M15: =M14*(1-$W$16) -> 3044697.5 | N15: =N14*(1-$W$16) -> 3552147 | O15: =O14*(1-$W$16) -> 4059596.6 | P15: =P14*(1-$W$16) -> 4567046.2 | Q15: =Q14*(1-$W$16) -> 2811038.4 | R15: =R14*(1-$W$16) -> 3373246.1 | S15: =S14*(1-$W$16) -> 3935453.8 | ... U15: =U14*(1-$W$16) -> 5059869.1 | W15: Post-OTA Revenues
W16: 0.15
F17: =F15*(1-$W$18) -> 1895626.3 | G17: =G15*(1-$W$18) -> 2274751.6 | H17: =H15*(1-$W$18) -> 2653876.8 | I17: =I15*(1-$W$18) -> 3033002.1 | J17: =J15*(1-$W$18) -> 3412127.3 | L17: =L15*(1-$W$18) -> 2105915.7 | M17: =M15*(1-$W$18) -> 2527098.9 | N17: =N15*(1-$W$18) -> 2948282 | O17: =O15*(1-$W$18) -> 3369465.2 | P17: =P15*(1-$W$18) -> 3790648.3 | Q17: =Q15*(1-$W$18) -> 2333161.9 | R17: =R15*(1-$W$18) -> 2799794.2 | S17: =S15*(1-$W$18) -> 3266426.6 | ... U17: =U15*(1-$W$18) -> 4199691.4 | W17: Net Revenue After deducting operaror fees
W18: 0.17
F21: =F17/SUM($L$6:$L$8) -> 22042.166 | G21: =G17/SUM($L$6:$L$8) -> 26450.599 | H21: =H17/SUM($L$6:$L$8) -> 30859.033 | I21: =I17/SUM($L$6:$L$8) -> 35267.466 | J21: =J17/SUM($L$6:$L$8) -> 39675.899 | L21: =L17/SUM($L$6:$L$8) -> 24487.392 | M21: =M17/SUM($L$6:$L$8) -> 29384.871 | N21: =N17/SUM($L$6:$L$8) -> 34282.349 | O21: =O17/SUM($L$6:$L$8) -> 39179.828 | P21: =P17/SUM($L$6:$L$8) -> 44077.306 | Q21: =Q17/SUM($L$6:$L$8) -> 27129.789 | R21: =R17/SUM($L$6:$L$8) -> 32555.747 | S21: =S17/SUM($L$6:$L$8) -> 37981.705 | ... U21: =U17/SUM($L$6:$L$8) -> 48833.621 | W21: Annual Revenue Per Unit
G22: =G14-#REF! -> #REF! | H22: =H14-#REF! -> #REF! | I22: =I14-#REF! -> #REF! | J22: =J14-#REF! -> #REF! | M22: =M14-#REF! -> #REF! | N22: =N14-#REF! -> #REF! | O22: =O14-#REF! -> #REF! | P22: =P14-#REF! -> #REF! | R22: =R14-#REF! -> #REF! | S22: =S14-#REF! -> #REF! | T22: =T14-#REF! -> #REF! | U22: =U14-#REF! -> #REF! | W22: Mathwa Gross Annual Commision
G23: =G22/18 -> #REF! | H23: =H22/18 -> #REF! | I23: =I22/18 -> #REF! | J23: =J22/18 -> #REF! | M23: =M22/18 -> #REF! | N23: =N22/18 -> #REF! | O23: =O22/18 -> #REF! | P23: =P22/18 -> #REF! | R23: =R22/18 -> #REF! | S23: =S22/18 -> #REF! | T23: =T22/18 -> #REF! | U23: =U22/18 -> #REF! | W23: Annual Commission per Unit
G24: =G23/' LTR Financial Study'!$I$7 -> #REF! | H24: =H23/' LTR Financial Study'!$I$7 -> #REF! | I24: =I23/' LTR Financial Study'!$I$7 -> #REF! | J24: =J23/' LTR Financial Study'!$I$7 -> #REF! | M24: =M23/#REF! -> #REF! | N24: =N23/#REF! -> #REF! | O24: =O23/#REF! -> #REF! | P24: =P23/#REF! -> #REF! | R24: =R23/' LTR Financial Study'!$J$7 -> #REF! | S24: =S23/' LTR Financial Study'!$J$7 -> #REF! | T24: =T23/' LTR Financial Study'!$J$7 -> #REF! | U24: =U23/' LTR Financial Study'!$J$7 -> #REF! | W24: Commission-To-Rent Ratio
F25: =F21/12 -> 1836.8472 | G25: =G21/12 -> 2204.2166 | H25: =H21/12 -> 2571.5861 | I25: =I21/12 -> 2938.9555 | J25: =J21/12 -> 3306.3249 | L25: =L21/12 -> 2040.616 | M25: =M21/12 -> 2448.7392 | N25: =N21/12 -> 2856.8624 | O25: =O21/12 -> 3264.9856 | P25: =P21/12 -> 3673.1088 | Q25: =Q21/12 -> 2260.8158 | R25: =R21/12 -> 2712.9789 | S25: =S21/12 -> 3165.1421 | ... U25: =U21/12 -> 4069.4684 | W25: Monthly Revenue Per Unit
F29: =F15-F17 -> 388260.81 | G29: =G15-G17 -> 465912.97 | H29: =H15-H17 -> 543565.13 | I29: =I15-I17 -> 621217.29 | J29: =J15-J17 -> 698869.45 | L29: =L15-L17 -> 431332.14 | M29: =M15-M17 -> 517598.57 | N29: =N15-N17 -> 603864.99 | O29: =O15-O17 -> 690131.42 | P29: =P15-P17 -> 776397.85 | Q29: =Q15-Q17 -> 477876.53 | R29: =R15-R17 -> 573451.83 | S29: =S15-S17 -> 669027.14 | ... U29: =U15-U17 -> 860177.75 | W29: Operator Annual Revenue
F30: =F29/12 -> 32355.067 | G30: =G29/12 -> 38826.081 | H30: =H29/12 -> 45297.094 | I30: =I29/12 -> 51768.108 | J30: =J29/12 -> 58239.121 | L30: =L29/12 -> 35944.345 | M30: =M29/12 -> 43133.214 | N30: =N29/12 -> 50322.083 | O30: =O29/12 -> 57510.952 | P30: =P29/12 -> 64699.821 | Q30: =Q29/12 -> 39823.044 | R30: =R29/12 -> 47787.653 | S30: =S29/12 -> 55752.262 | ... U30: =U29/12 -> 71681.479 | W30: Operator Monthly Revenue

Sheet Hybrid Projection
O5: No. of units | P5: Type
O6: 54 | P6: 1Bd
O7: 29 | P7: 2Bd
F8: Assuming STR Occupancy rate | H8: 1 | O8: 3 | P8: 3BR
F9: Assuming LTR Occupancy Rate | H9: 1
F13: Base Scenario
E14: Month | F14: January | G14: February | H14: March | I14: April | J14: May | K14: June | L14: July | M14: August | N14: September | O14: October | P14: November | Q14: December | R14: Total
E15: Type | F15: STR | G15: STR | H15: STR | I15: LTR | J15: LTR | K15: LTR | L15: LTR | M15: LTR | N15: LTR | O15: LTR | P15: LTR | Q15: STR
E16: Revenue | F16: =('STR-Regular Financial Study'!$I$94/12)*$H$8 -> 1237450.9 | G16: =('STR-Regular Financial Study'!$I$94/12)*$H$8 -> 1237450.9 | H16: =('STR-Regular Financial Study'!$I$94/12)*$H$8 -> 1237450.9 | I16: =SUM('LTR-Regular Financial Study'!$I$7:$I$92)*$H$9 -> 497499.58 | J16: =SUM('LTR-Regular Financial Study'!$I$7:$I$92)*$H$9 -> 497499.58 | K16: =SUM('LTR-Regular Financial Study'!$I$7:$I$92)*$H$9 -> 497499.58 | L16: =SUM('LTR-Regular Financial Study'!$I$7:$I$92)*$H$9 -> 497499.58 | M16: =SUM('LTR-Regular Financial Study'!$I$7:$I$92)*$H$9 -> 497499.58 | N16: =SUM('LTR-Regular Financial Study'!$I$7:$I$92)*$H$9 -> 497499.58 | O16: =SUM('LTR-Regular Financial Study'!$I$7:$I$92)*$H$9 -> 497499.58 | P16: =SUM('LTR-Regular Financial Study'!$I$7:$I$92)*$H$9 -> 497499.58 | Q16: =('STR-Regular Financial Study'!$I$94/12)*$H$8 -> 1237450.9 | R16: =SUM(F16:Q16) -> 8929800.2
D17: 0.17 | E17: Operator Fees | F17: =F16*$D$17 -> 210366.65 | G17: =G16*$D$17 -> 210366.65 | H17: =H16*$D$17 -> 210366.65 | I17: =I16*$D$17 -> 84574.929 | J17: =J16*$D$17 -> 84574.929 | K17: =K16*$D$17 -> 84574.929 | L17: =L16*$D$17 -> 84574.929 | M17: =M16*$D$17 -> 84574.929 | ... Q17: =Q16*$D$17 -> 210366.65 | R17: =SUM(F17:Q17) -> 1518066
E18: Net to Owner | F18: =F16-F17 -> 1027084.2 | G18: =G16-G17 -> 1027084.2 | H18: =H16-H17 -> 1027084.2 | I18: =I16-I17 -> 412924.65 | J18: =J16-J17 -> 412924.65 | K18: =K16-K17 -> 412924.65 | L18: =L16-L17 -> 412924.65 | M18: =M16-M17 -> 412924.65 | ... Q18: =Q16-Q17 -> 1027084.2 | R18: =SUM(F18:Q18) -> 7411734.2
F23: Pessimestic Scenario
E24: Month | F24: January | G24: February | H24: March | I24: April | J24: May | K24: June | L24: July | M24: August | N24: September | O24: October | P24: November | Q24: December | R24: Total
E25: Type | F25: STR | G25: STR | H25: STR | I25: LTR | J25: LTR | K25: LTR | L25: LTR | M25: LTR | N25: LTR | O25: LTR | P25: LTR | Q25: STR
E26: Revenue | F26: =('STR-Regular Financial Study'!$J$94/12)*$H$8 -> 1071900 | G26: =('STR-Regular Financial Study'!$J$94/12)*$H$8 -> 1071900 | H26: =('STR-Regular Financial Study'!$J$94/12)*$H$8 -> 1071900 | I26: =SUM('LTR-Regular Financial Study'!$J$7:$J$92)*$H$9 -> 447821 | J26: =SUM('LTR-Regular Financial Study'!$J$7:$J$92)*$H$9 -> 447821 | K26: =SUM('LTR-Regular Financial Study'!$J$7:$J$92)*$H$9 -> 447821 | L26: =SUM('LTR-Regular Financial Study'!$J$7:$J$92)*$H$9 -> 447821 | M26: =SUM('LTR-Regular Financial Study'!$J$7:$J$92)*$H$9 -> 447821 | N26: =SUM('LTR-Regular Financial Study'!$J$7:$J$92)*$H$9 -> 447821 | O26: =SUM('LTR-Regular Financial Study'!$J$7:$J$92)*$H$9 -> 447821 | P26: =SUM('LTR-Regular Financial Study'!$J$7:$J$92)*$H$9 -> 447821 | Q26: =('STR-Regular Financial Study'!$J$94/12)*$H$8 -> 1071900 | R26: =SUM(F26:Q26) -> 7870168
D27: 0.17 | E27: Operator Fees | F27: =F26*$D$27 -> 182223 | G27: =G26*$D$27 -> 182223 | H27: =H26*$D$27 -> 182223 | I27: =I26*$D$27 -> 76129.57 | J27: =J26*$D$27 -> 76129.57 | K27: =K26*$D$27 -> 76129.57 | L27: =L26*$D$27 -> 76129.57 | M27: =M26*$D$27 -> 76129.57 | ... Q27: =Q26*$D$27 -> 182223 | R27: =SUM(F27:Q27) -> 1337928.6
E28: Net to Owner | F28: =F26-F27 -> 889677 | G28: =G26-G27 -> 889677 | H28: =H26-H27 -> 889677 | I28: =I26-I27 -> 371691.43 | J28: =J26-J27 -> 371691.43 | K28: =K26-K27 -> 371691.43 | L28: =L26-L27 -> 371691.43 | M28: =M26-M27 -> 371691.43 | ... Q28: =Q26-Q27 -> 889677 | R28: =SUM(F28:Q28) -> 6532239.4
F32: Optimistic Scenario
E33: Month | F33: January | G33: February | H33: March | I33: April | J33: May | K33: June | L33: July | M33: August | N33: September | O33: October | P33: November | Q33: December | R33: Total
E34: Type | F34: STR | G34: STR | H34: STR | I34: LTR | J34: LTR | K34: LTR | L34: LTR | M34: LTR | N34: LTR | O34: LTR | P34: LTR | Q34: STR
E35: Revenue | F35: =('STR-Regular Financial Study'!$H$94/12)*$H$8 -> 1402590 | G35: =('STR-Regular Financial Study'!$H$94/12)*$H$8 -> 1402590 | H35: =('STR-Regular Financial Study'!$H$94/12)*$H$8 -> 1402590 | I35: =SUM('LTR-Regular Financial Study'!$H$7:$H$92)*$H$9 -> 551184 | J35: =SUM('LTR-Regular Financial Study'!$H$7:$H$92)*$H$9 -> 551184 | K35: =SUM('LTR-Regular Financial Study'!$H$7:$H$92)*$H$9 -> 551184 | L35: =SUM('LTR-Regular Financial Study'!$H$7:$H$92)*$H$9 -> 551184 | M35: =SUM('LTR-Regular Financial Study'!$H$7:$H$92)*$H$9 -> 551184 | N35: =SUM('LTR-Regular Financial Study'!$H$7:$H$92)*$H$9 -> 551184 | O35: =SUM('LTR-Regular Financial Study'!$H$7:$H$92)*$H$9 -> 551184 | P35: =SUM('LTR-Regular Financial Study'!$H$7:$H$92)*$H$9 -> 551184 | Q35: =('STR-Regular Financial Study'!$H$94/12)*$H$8 -> 1402590 | R35: =SUM(F35:Q35) -> 10019832
D36: 0.17 | E36: Operator Fees | F36: =F35*$D$36 -> 238440.3 | G36: =G35*$D$36 -> 238440.3 | H36: =H35*$D$36 -> 238440.3 | I36: =I35*$D$36 -> 93701.28 | J36: =J35*$D$36 -> 93701.28 | K36: =K35*$D$36 -> 93701.28 | L36: =L35*$D$36 -> 93701.28 | M36: =M35*$D$36 -> 93701.28 | ... Q36: =Q35*$D$36 -> 238440.3 | R36: =SUM(F36:Q36) -> 1703371.4
E37: Net to Owner | F37: =F35-F36 -> 1164149.7 | G37: =G35-G36 -> 1164149.7 | H37: =H35-H36 -> 1164149.7 | I37: =I35-I36 -> 457482.72 | J37: =J35-J36 -> 457482.72 | K37: =K35-K36 -> 457482.72 | L37: =L35-L36 -> 457482.72 | M37: =M35-M36 -> 457482.72 | ... Q37: =Q35-Q36 -> 1164149.7 | R37: =SUM(F37:Q37) -> 8316460.6

Sheet Hybrid Model Study Summary
L5: No. of units | M5: Type
L6: =COUNTA('STR-Regular Financial Study'!L7:L60) -> 54 | M6: 1Bd
L7: =COUNTA('STR-Regular Financial Study'!L61:L89) -> 29 | M7: 2Bd
L8: =3 -> 3 | M8: 3BR
F10: Financial Study - Leora
F11: Worst Case | L11: Base Case | Q11: Best Case | W11: Scenarios
F12: ='Hybrid Projection'!R26 -> 7870168 | L12: ='Hybrid Projection'!R16 -> 8929800.2 | Q12: ='Hybrid Projection'!R35 -> 10019832 | W12: Revenue at 100% occupancy
F13: 0.5 | G13: 0.6 | H13: 0.7 | I13: 0.8 | J13: 0.9 | L13: 0.5 | M13: 0.6 | N13: 0.7 | O13: 0.8 | P13: 0.9 | Q13: 0.5 | R13: 0.6 | S13: 0.7 | T13: 0.8 | U13: 0.9 | W13: Varying occupancy scenario
F14: =$F$12*F13 -> 3935084 | G14: =$F$12*G13 -> 4722100.8 | H14: =$F$12*H13 -> 5509117.6 | I14: =$F$12*I13 -> 6296134.4 | J14: =$F$12*J13 -> 7083151.2 | L14: =$L$12*L13 -> 4464900.1 | M14: =$L$12*M13 -> 5357880.1 | N14: =$L$12*N13 -> 6250860.1 | O14: =$L$12*O13 -> 7143840.1 | P14: =$L$12*P13 -> 8036820.2 | Q14: =$Q$12*Q13 -> 5009916 | R14: =$Q$12*R13 -> 6011899.2 | S14: =$Q$12*S13 -> 7013882.4 | T14: =$Q$12*T13 -> 8015865.6 | U14: =$Q$12*U13 -> 9017848.8 | W14: Revenue pre deductions
F15: =F14*(1-$W$16) -> 3344821.4 | G15: =G14*(1-$W$16) -> 4013785.7 | H15: =H14*(1-$W$16) -> 4682750 | I15: =I14*(1-$W$16) -> 5351714.2 | J15: =J14*(1-$W$16) -> 6020678.5 | L15: =L14*(1-$W$16) -> 3795165.1 | M15: =M14*(1-$W$16) -> 4554198.1 | N15: =N14*(1-$W$16) -> 5313231.1 | O15: =O14*(1-$W$16) -> 6072264.1 | P15: =P14*(1-$W$16) -> 6831297.1 | Q15: =Q14*(1-$W$16) -> 4258428.6 | R15: =R14*(1-$W$16) -> 5110114.3 | S15: =S14*(1-$W$16) -> 5961800 | ... U15: =U14*(1-$W$16) -> 7665171.5 | W15: Post-OTA Revenues
W16: 0.15
F17: =F15*(1-$W$18) -> 2776201.8 | G17: =G15*(1-$W$18) -> 3331442.1 | H17: =H15*(1-$W$18) -> 3886682.5 | I17: =I15*(1-$W$18) -> 4441922.8 | J17: =J15*(1-$W$18) -> 4997163.2 | L17: =L15*(1-$W$18) -> 3149987 | M17: =M15*(1-$W$18) -> 3779984.4 | N17: =N15*(1-$W$18) -> 4409981.8 | O17: =O15*(1-$W$18) -> 5039979.2 | P17: =P15*(1-$W$18) -> 5669976.6 | Q17: =Q15*(1-$W$18) -> 3534495.7 | R17: =R15*(1-$W$18) -> 4241394.9 | S17: =S15*(1-$W$18) -> 4948294 | ... U17: =U15*(1-$W$18) -> 6362092.3 | W17: Net Revenue After deducting operaror fees
W18: 0.17
F21: =F17/SUM($L$6:$L$8) -> 32281.416 | G21: =G17/SUM($L$6:$L$8) -> 38737.699 | H21: =H17/SUM($L$6:$L$8) -> 45193.982 | I21: =I17/SUM($L$6:$L$8) -> 51650.265 | J21: =J17/SUM($L$6:$L$8) -> 58106.549 | L21: =L17/SUM($L$6:$L$8) -> 36627.756 | M21: =M17/SUM($L$6:$L$8) -> 43953.307 | N21: =N17/SUM($L$6:$L$8) -> 51278.858 | O21: =O17/SUM($L$6:$L$8) -> 58604.41 | P21: =P17/SUM($L$6:$L$8) -> 65929.961 | Q21: =Q17/SUM($L$6:$L$8) -> 41098.788 | R21: =R17/SUM($L$6:$L$8) -> 49318.545 | S21: =S17/SUM($L$6:$L$8) -> 57538.303 | ... U21: =U17/SUM($L$6:$L$8) -> 73977.818 | W21: Annual Revenue Per Unit
G22: =G14-#REF! -> #REF! | H22: =H14-#REF! -> #REF! | I22: =I14-#REF! -> #REF! | J22: =J14-#REF! -> #REF! | M22: =M14-#REF! -> #REF! | N22: =N14-#REF! -> #REF! | O22: =O14-#REF! -> #REF! | P22: =P14-#REF! -> #REF! | R22: =R14-#REF! -> #REF! | S22: =S14-#REF! -> #REF! | T22: =T14-#REF! -> #REF! | U22: =U14-#REF! -> #REF! | W22: Mathwa Gross Annual Commision
G23: =G22/18 -> #REF! | H23: =H22/18 -> #REF! | I23: =I22/18 -> #REF! | J23: =J22/18 -> #REF! | M23: =M22/18 -> #REF! | N23: =N22/18 -> #REF! | O23: =O22/18 -> #REF! | P23: =P22/18 -> #REF! | R23: =R22/18 -> #REF! | S23: =S22/18 -> #REF! | T23: =T22/18 -> #REF! | U23: =U22/18 -> #REF! | W23: Annual Commission per Unit
G24: =G23/' LTR Financial Study'!$I$7 -> #REF! | H24: =H23/' LTR Financial Study'!$I$7 -> #REF! | I24: =I23/' LTR Financial Study'!$I$7 -> #REF! | J24: =J23/' LTR Financial Study'!$I$7 -> #REF! | M24: =M23/#REF! -> #REF! | N24: =N23/#REF! -> #REF! | O24: =O23/#REF! -> #REF! | P24: =P23/#REF! -> #REF! | R24: =R23/' LTR Financial Study'!$J$7 -> #REF! | S24: =S23/' LTR Financial Study'!$J$7 -> #REF! | T24: =T23/' LTR Financial Study'!$J$7 -> #REF! | U24: =U23/' LTR Financial Study'!$J$7 -> #REF! | W24: Commission-To-Rent Ratio
F25: =F21/12 -> 2690.118 | G25: =G21/12 -> 3228.1416 | H25: =H21/12 -> 3766.1652 | I25: =I21/12 -> 4304.1888 | J25: =J21/12 -> 4842.2124 | L25: =L21/12 -> 3052.313 | M25: =M21/12 -> 3662.7756 | N25: =N21/12 -> 4273.2382 | O25: =O21/12 -> 4883.7008 | P25: =P21/12 -> 5494.1634 | Q25: =Q21/12 -> 3424.899 | R25: =R21/12 -> 4109.8788 | S25: =S21/12 -> 4794.8586 | ... U25: =U21/12 -> 6164.8181 | W25: Monthly Revenue Per Unit
F29: =F15-F17 -> 568619.64 | G29: =G15-G17 -> 682343.57 | H29: =H15-H17 -> 796067.49 | I29: =I15-I17 -> 909791.42 | J29: =J15-J17 -> 1023515.3 | L29: =L15-L17 -> 645178.06 | M29: =M15-M17 -> 774213.68 | N29: =N15-N17 -> 903249.29 | O29: =O15-O17 -> 1032284.9 | P29: =P15-P17 -> 1161320.5 | Q29: =Q15-Q17 -> 723932.86 | R29: =R15-R17 -> 868719.43 | S29: =S15-S17 -> 1013506 | ... U29: =U15-U17 -> 1303079.2 | W29: Operator Annual Revenue
F30: =F29/12 -> 47384.97 | G30: =G29/12 -> 56861.964 | H30: =H29/12 -> 66338.958 | I30: =I29/12 -> 75815.952 | J30: =J29/12 -> 85292.946 | L30: =L29/12 -> 53764.839 | M30: =M29/12 -> 64517.806 | N30: =N29/12 -> 75270.774 | O30: =O29/12 -> 86023.742 | P30: =P29/12 -> 96776.709 | Q30: =Q29/12 -> 60327.738 | R30: =R29/12 -> 72393.286 | S30: =S29/12 -> 84458.834 | ... U30: =U29/12 -> 108589.93 | W30: Operator Monthly Revenue

Sheet Co-Living Financial Study
E5: No. of units | F5: Type
E6: 5 | F6: 3BR | H6: Best Case | I6: Base Case | J6: Worst Case | K6: Type | L6: Unit
A7: Assumptions | E7: 4 | F7: 2BR | H7: =$B$8*VALUE(LEFT($K7,1)) -> 11100 | I7: =$B$9*VALUE(LEFT($K7,1)) -> 10500 | J7: =$B$10*VALUE(LEFT($K7,1)) -> 9600 | K7: 3BR | L7: {=SEQUENCE(9,1,1,1)} -> 1
A8: {=TRANSPOSE(H6:J6)} -> Best Case | B8: 3700 | H8: =$B$8*VALUE(LEFT($K8,1)) -> 11100 | I8: =$B$9*VALUE(LEFT($K8,1)) -> 10500 | J8: =$B$10*VALUE(LEFT($K8,1)) -> 9600 | K8: 3BR | L8: 2
A9: Base Case | B9: 3500 | H9: =$B$8*VALUE(LEFT($K9,1)) -> 7400 | I9: =$B$9*VALUE(LEFT($K9,1)) -> 7000 | J9: =$B$10*VALUE(LEFT($K9,1)) -> 6400 | K9: 2BR | L9: 3
A10: Worst Case | B10: 3200 | H10: =$B$8*VALUE(LEFT($K10,1)) -> 7400 | I10: =$B$9*VALUE(LEFT($K10,1)) -> 7000 | J10: =$B$10*VALUE(LEFT($K10,1)) -> 6400 | K10: 2BR | L10: 4
H11: =$B$8*VALUE(LEFT($K11,1)) -> 11100 | I11: =$B$9*VALUE(LEFT($K11,1)) -> 10500 | J11: =$B$10*VALUE(LEFT($K11,1)) -> 9600 | K11: 3BR | L11: 5
H12: =$B$8*VALUE(LEFT($K12,1)) -> 11100 | I12: =$B$9*VALUE(LEFT($K12,1)) -> 10500 | J12: =$B$10*VALUE(LEFT($K12,1)) -> 9600 | K12: 3BR | L12: 6
H13: =$B$8*VALUE(LEFT($K13,1)) -> 11100 | I13: =$B$9*VALUE(LEFT($K13,1)) -> 10500 | J13: =$B$10*VALUE(LEFT($K13,1)) -> 9600 | K13: 3BR | L13: 7
H14: =$B$8*VALUE(LEFT($K14,1)) -> 7400 | I14: =$B$9*VALUE(LEFT($K14,1)) -> 7000 | J14: =$B$10*VALUE(LEFT($K14,1)) -> 6400 | K14: 2BR | L14: 8
H15: =$B$8*VALUE(LEFT($K15,1)) -> 7400 | I15: =$B$9*VALUE(LEFT($K15,1)) -> 7000 | J15: =$B$10*VALUE(LEFT($K15,1)) -> 6400 | K15: 2BR | L15: 9
H17: =SUM(H7:H15)*12 -> 1021200 | I17: =SUM(I7:I15)*12 -> 966000 | J17: =SUM(J7:J15)*12 -> 883200 | K17: Total

Sheet Co-Living Study Summary
L5: No. of units | M5: Type
L6: 5 | M6: 3BR
L7: 4 | M7: 2BR
H10: Financial Study
F11: Worst Case | L11: Base Case | Q11: Best Case | W11: Scenarios
F12: ='Co-Living Financial Study'!J17 -> 883200 | L12: ='Co-Living Financial Study'!I17 -> 966000 | Q12: ='Co-Living Financial Study'!H17 -> 1021200 | W12: Revenue at 100% occupancy
F13: 0.5 | G13: 0.6 | H13: 0.7 | I13: 0.8 | J13: 0.9 | L13: 0.5 | M13: 0.6 | N13: 0.7 | O13: 0.8 | P13: 0.9 | Q13: 0.5 | R13: 0.6 | S13: 0.7 | T13: 0.8 | U13: 0.9 | W13: Varying occupancy scenario
F14: =$F$12*F13 -> 441600 | G14: =$F$12*G13 -> 529920 | H14: =$F$12*H13 -> 618240 | I14: =$F$12*I13 -> 706560 | J14: =$F$12*J13 -> 794880 | L14: =$L$12*L13 -> 483000 | M14: =$L$12*M13 -> 579600 | N14: =$L$12*N13 -> 676200 | O14: =$L$12*O13 -> 772800 | P14: =$L$12*P13 -> 869400 | Q14: =$Q$12*Q13 -> 510600 | R14: =$Q$12*R13 -> 612720 | S14: =$Q$12*S13 -> 714840 | T14: =$Q$12*T13 -> 816960 | U14: =$Q$12*U13 -> 919080 | W14: Revenue pre deductions
F15: =F14*(1-$W$16) -> 353280 | G15: =G14*(1-$W$16) -> 423936 | H15: =H14*(1-$W$16) -> 494592 | I15: =I14*(1-$W$16) -> 565248 | J15: =J14*(1-$W$16) -> 635904 | L15: =L14*(1-$W$16) -> 386400 | M15: =M14*(1-$W$16) -> 463680 | N15: =N14*(1-$W$16) -> 540960 | O15: =O14*(1-$W$16) -> 618240 | P15: =P14*(1-$W$16) -> 695520 | Q15: =Q14*(1-$W$16) -> 408480 | R15: =R14*(1-$W$16) -> 490176 | S15: =S14*(1-$W$16) -> 571872 | ... U15: =U14*(1-$W$16) -> 735264 | W15: Net Revenue After deducting operaror fees
W16: 0.2
F19: =F15/SUM($L$6:$L$7) -> 39253.333 | G19: =G15/SUM($L$6:$L$7) -> 47104 | H19: =H15/SUM($L$6:$L$7) -> 54954.667 | I19: =I15/SUM($L$6:$L$7) -> 62805.333 | J19: =J15/SUM($L$6:$L$7) -> 70656 | L19: =L15/SUM($L$6:$L$7) -> 42933.333 | M19: =M15/SUM($L$6:$L$7) -> 51520 | N19: =N15/SUM($L$6:$L$7) -> 60106.667 | O19: =O15/SUM($L$6:$L$7) -> 68693.333 | P19: =P15/SUM($L$6:$L$7) -> 77280 | Q19: =Q15/SUM($L$6:$L$7) -> 45386.667 | R19: =R15/SUM($L$6:$L$7) -> 54464 | S19: =S15/SUM($L$6:$L$7) -> 63541.333 | ... U19: =U15/SUM($L$6:$L$7) -> 81696 | W19: Annual Revenue Per Unit
G20: =G14-#REF! -> #REF! | H20: =H14-#REF! -> #REF! | I20: =I14-#REF! -> #REF! | J20: =J14-#REF! -> #REF! | M20: =M14-#REF! -> #REF! | N20: =N14-#REF! -> #REF! | O20: =O14-#REF! -> #REF! | P20: =P14-#REF! -> #REF! | R20: =R14-#REF! -> #REF! | S20: =S14-#REF! -> #REF! | T20: =T14-#REF! -> #REF! | U20: =U14-#REF! -> #REF! | W20: Mathwa Gross Annual Commision
G21: =G20/18 -> #REF! | H21: =H20/18 -> #REF! | I21: =I20/18 -> #REF! | J21: =J20/18 -> #REF! | M21: =M20/18 -> #REF! | N21: =N20/18 -> #REF! | O21: =O20/18 -> #REF! | P21: =P20/18 -> #REF! | R21: =R20/18 -> #REF! | S21: =S20/18 -> #REF! | T21: =T20/18 -> #REF! | U21: =U20/18 -> #REF! | W21: Annual Commission per Unit
G22: =G21/' LTR Financial Study'!$I$7 -> #REF! | H22: =H21/' LTR Financial Study'!$I$7 -> #REF! | I22: =I21/' LTR Financial Study'!$I$7 -> #REF! | J22: =J21/' LTR Financial Study'!$I$7 -> #REF! | M22: =M21/#REF! -> #REF! | N22: =N21/#REF! -> #REF! | O22: =O21/#REF! -> #REF! | P22: =P21/#REF! -> #REF! | R22: =R21/' LTR Financial Study'!$J$7 -> #REF! | S22: =S21/' LTR Financial Study'!$J$7 -> #REF! | T22: =T21/' LTR Financial Study'!$J$7 -> #REF! | U22: =U21/' LTR Financial Study'!$J$7 -> #REF! | W22: Commission-To-Rent Ratio
F23: =F19/12 -> 3271.1111 | G23: =G19/12 -> 3925.3333 | H23: =H19/12 -> 4579.5556 | I23: =I19/12 -> 5233.7778 | J23: =J19/12 -> 5888 | L23: =L19/12 -> 3577.7778 | M23: =M19/12 -> 4293.3333 | N23: =N19/12 -> 5008.8889 | O23: =O19/12 -> 5724.4444 | P23: =P19/12 -> 6440 | Q23: =Q19/12 -> 3782.2222 | R23: =R19/12 -> 4538.6667 | S23: =S19/12 -> 5295.1111 | ... U23: =U19/12 -> 6808 | W23: Monthly Revenue Per Unit
H28: =' LTR Financial Study'!C17
